{ "name": "rdkafka#producer-37", "client_id": "rdkafka", "type": "producer", "ts":13380526147, "time":1682592786, "age":2000198, "replyq":0, "msg_cnt":95800, "msg_size":766400, "msg_max":100000, "msg_size_max":1073741824, "simple_cnt":0, "metadata_cache_cnt":1, "brokers":{ "192.168.0.131:9092/0": { "name":"192.168.0.131:9092/0", "nodeid":0, "nodename":"192.168.0.131:9092", "source":"configured", "state":"UP", "stateage":1897060, "outbuf_cnt":0, "outbuf_msg_cnt":0, "waitresp_cnt":1, "waitresp_msg_cnt":10000, "tx":151, "txbytes":12970296, "txerrs":0, "txretries":0, "txidle":849, "req_timeouts":0, "rx":150, "rxbytes":9591, "rxerrs":0, "rxcorriderrs":0, "rxpartial":0, "rxidle":3526, "zbuf_grow":0, "buf_grow":0, "wakeups":157, "connects":1, "disconnects":0, "int_latency": { "min":75536, "max":179388, "avg":102749, "sum":151191223456, "stddev": 7322, "p50": 102399, "p75": 105471, "p90": 108543, "p95": 109567, "p99": 117759, "p99_99": 130559, "outofrange": 53132, "hdrsize": 11376, "cnt":1471451 }, "outbuf_latency": { "min":8, "max":5049, "avg":2184, "sum":329873, "stddev": 1087, "p50": 2319, "p75": 2591, "p90": 2879, "p95": 4383, "p99": 4799, "p99_99": 5055, "outofrange": 0, "hdrsize": 11376, "cnt":151 }, "rtt": { "min":2828, "max":32492, "avg":12478, "sum":1871710, "stddev": 4499, "p50": 11007, "p75": 11455, "p90": 19455, "p95": 23295, "p99": 30847, "p99_99": 32511, "outofrange": 0, "hdrsize": 13424, "cnt":150 }, "throttle": { "min":0, "max":0, "avg":0, "sum":0, "stddev": 0, "p50": 0, "p75": 0, "p90": 0, "p95": 0, "p99": 0, "p99_99": 0, "outofrange": 0, "hdrsize": 17520, "cnt":0 }, "req": { "Produce": 149, "ListOffsets": 0, "Metadata": 1, "FindCoordinator": 0, "SaslHandshake": 0, "ApiVersion": 1, "InitProducerId": 0, "AddPartitionsToTxn": 0, "AddOffsetsToTxn": 0, "EndTxn": 0, "TxnOffsetCommit": 0, "SaslAuthenticate": 0, "OffsetDeleteRequest": 0, "DescribeClientQuotasRequest": 0, "AlterClientQuotasRequest": 0, "DescribeUserScramCredentialsRequest": 0 }, "toppars":{ "benchmark-0": { "topic":"benchmark", "partition":0} } } }, "topics":{ "benchmark": { "topic":"benchmark", "age":1999, "metadata_age":1897, "batchsize": { "min":196, "max":90756, "avg":86992, "sum":12961875, "stddev": 10178, "p50": 88575, "p75": 89599, "p90": 89599, "p95": 90111, "p99": 90623, "p99_99": 91135, "outofrange": 0, "hdrsize": 14448, "cnt":149 }, "batchcnt": { "min":9, "max":10000, "avg":9844, "sum":1466868, "stddev": 1152, "p50": 10047, "p75": 10047, "p90": 10047, "p95": 10047, "p99": 10047, "p99_99": 10047, "outofrange": 0, "hdrsize": 8304, "cnt":149 }, "partitions":{ "0": { "partition":0, "broker":0, "leader":0, "desired":false, "unknown":false, "msgq_cnt":1324, "msgq_bytes":10592, "xmit_msgq_cnt":0, "xmit_msgq_bytes":0, "fetchq_cnt":0, "fetchq_size":0, "fetch_state":"none", "query_offset":-1001, "next_offset":0, "app_offset":-1001, "stored_offset":-1001, "commited_offset":-1001, "committed_offset":-1001, "eof_offset":-1001, "lo_offset":-1001, "hi_offset":-1001, "ls_offset":-1001, "consumer_lag":-1, "consumer_lag_stored":-1, "txmsgs":1466868, "txbytes":11734944, "rxmsgs":0, "rxbytes":0, "msgs": 1552668, "rx_ver_drops": 0, "msgs_inflight": 10000, "next_ack_seq": 0, "next_err_seq": 0, "acked_msgid": 0} , "-1": { "partition":-1, "broker":-1, "leader":-1, "desired":false, "unknown":false, "msgq_cnt":0, "msgq_bytes":0, "xmit_msgq_cnt":0, "xmit_msgq_bytes":0, "fetchq_cnt":0, "fetchq_size":0, "fetch_state":"none", "query_offset":-1001, "next_offset":0, "app_offset":-1001, "stored_offset":-1001, "commited_offset":-1001, "committed_offset":-1001, "eof_offset":-1001, "lo_offset":-1001, "hi_offset":-1001, "ls_offset":-1001, "consumer_lag":-1, "consumer_lag_stored":-1, "txmsgs":0, "txbytes":0, "rxmsgs":0, "rxbytes":0, "msgs": 100000, "rx_ver_drops": 0, "msgs_inflight": 0, "next_ack_seq": 0, "next_err_seq": 0, "acked_msgid": 0} } } } , "tx":151, "tx_bytes":12970296, "rx":150, "rx_bytes":9591, "txmsgs":1466868, "txmsg_bytes":11734944, "rxmsgs":0, "rxmsg_bytes":0}
{ "name": "rdkafka#producer-37", "client_id": "rdkafka", "type": "producer", "ts":13382526482, "time":1682592788, "age":4000533, "replyq":0, "msg_cnt":0, "msg_size":0, "msg_max":100000, "msg_size_max":1073741824, "simple_cnt":0, "metadata_cache_cnt":1, "brokers":{ "192.168.0.131:9092/0": { "name":"192.168.0.131:9092/0", "nodeid":0, "nodename":"192.168.0.131:9092", "source":"configured", "state":"UP", "stateage":3897395, "outbuf_cnt":0, "outbuf_msg_cnt":0, "waitresp_cnt":0, "waitresp_msg_cnt":0, "tx":325, "txbytes":28178249, "txerrs":0, "txretries":0, "txidle":100288, "req_timeouts":0, "rx":325, "rxbytes":20266, "rxerrs":0, "rxcorriderrs":0, "rxpartial":0, "rxidle":91723, "zbuf_grow":0, "buf_grow":0, "wakeups":333, "connects":1, "disconnects":0, "int_latency": { "min":31355, "max":109559, "avg":80498, "sum":139260872429, "stddev": 11049, "p50": 81407, "p75": 86015, "p90": 89599, "p95": 102399, "p99": 107519, "p99_99": 109567, "outofrange": 0, "hdrsize": 12400, "cnt":1729978 }, "outbuf_latency": { "min":10, "max":6137, "avg":2342, "sum":407565, "stddev": 2238, "p50": 1975, "p75": 4831, "p90": 5215, "p95": 5599, "p99": 5759, "p99_99": 6143, "outofrange": 0, "hdrsize": 11376, "cnt":174 }, "rtt": { "min":8565, "max":31936, "avg":14890, "sum":2605791, "stddev": 4475, "p50": 15743, "p75": 17535, "p90": 18175, "p95": 23295, "p99": 29567, "p99_99": 31999, "outofrange": 0, "hdrsize": 13424, "cnt":175 }, "throttle": { "min":0, "max":0, "avg":0, "sum":0, "stddev": 0, "p50": 0, "p75": 0, "p90": 0, "p95": 0, "p99": 0, "p99_99": 0, "outofrange": 0, "hdrsize": 17520, "cnt":0 }, "req": { "Produce": 323, "ListOffsets": 0, "Metadata": 1, "FindCoordinator": 0, "SaslHandshake": 0, "ApiVersion": 1, "InitProducerId": 0, "AddPartitionsToTxn": 0, "AddOffsetsToTxn": 0, "EndTxn": 0, "TxnOffsetCommit": 0, "SaslAuthenticate": 0, "OffsetDeleteRequest": 0, "DescribeClientQuotasRequest": 0, "AlterClientQuotasRequest": 0, "DescribeUserScramCredentialsRequest": 0 }, "toppars":{ "benchmark-0": { "topic":"benchmark", "partition":0} } } }, "topics":{ "benchmark": { "topic":"benchmark", "age":3999, "metadata_age":3897, "batchsize": { "min":35121, "max":90446, "avg":87346, "sum":15198209, "stddev": 4390, "p50": 88575, "p75": 89087, "p90": 89599, "p95": 90111, "p99": 90111, "p99_99": 90623, "outofrange": 0, "hdrsize": 14448, "cnt":174 }, "batchcnt": { "min":4561, "max":10000, "avg":9968, "sum":1734561, "stddev": 412, "p50": 10047, "p75": 10047, "p90": 10047, "p95": 10047, "p99": 10047, "p99_99": 10047, "outofrange": 0, "hdrsize": 8304, "cnt":174 }, "partitions":{ "0": { "partition":0, "broker":0, "leader":0, "desired":false, "unknown":false, "msgq_cnt":0, "msgq_bytes":0, "xmit_msgq_cnt":0, "xmit_msgq_bytes":0, "fetchq_cnt":0, "fetchq_size":0, "fetch_state":"none", "query_offset":-1001, "next_offset":0, "app_offset":-1001, "stored_offset":-1001, "commited_offset":-1001, "committed_offset":-1001, "eof_offset":-1001, "lo_offset":-1001, "hi_offset":-1001, "ls_offset":-1001, "consumer_lag":-1, "consumer_lag_stored":-1, "txmsgs":3201429, "txbytes":25611432, "rxmsgs":0, "rxbytes":0, "msgs": 3201429, "rx_ver_drops": 0, "msgs_inflight": 0, "next_ack_seq": 0, "next_err_seq": 0, "acked_msgid": 0} , "-1": { "partition":-1, "broker":-1, "leader":-1, "desired":false, "unknown":false, "msgq_cnt":0, "msgq_bytes":0, "xmit_msgq_cnt":0, "xmit_msgq_bytes":0, "fetchq_cnt":0, "fetchq_size":0, "fetch_state":"none", "query_offset":-1001, "next_offset":0, "app_offset":-1001, "stored_offset":-1001, "commited_offset":-1001, "committed_offset":-1001, "eof_offset":-1001, "lo_offset":-1001, "hi_offset":-1001, "ls_offset":-1001, "consumer_lag":-1, "consumer_lag_stored":-1, "txmsgs":0, "txbytes":0, "rxmsgs":0, "rxbytes":0, "msgs": 100000, "rx_ver_drops": 0, "msgs_inflight": 0, "next_ack_seq": 0, "next_err_seq": 0, "acked_msgid": 0} } } } , "tx":325, "tx_bytes":28178249, "rx":325, "rx_bytes":20266, "txmsgs":3201429, "txmsg_bytes":25611432, "rxmsgs":0, "rxmsg_bytes":0}
{ "name": "rdkafka#producer-37", "client_id": "rdkafka", "type": "producer", "ts":13384527067, "time":1682592790, "age":6001118, "replyq":1, "msg_cnt":0, "msg_size":0, "msg_max":100000, "msg_size_max":1073741824, "simple_cnt":0, "metadata_cache_cnt":1, "brokers":{ "192.168.0.131:9092/0": { "name":"192.168.0.131:9092/0", "nodeid":0, "nodename":"192.168.0.131:9092", "source":"configured", "state":"UP", "stateage":5897980, "outbuf_cnt":0, "outbuf_msg_cnt":0, "waitresp_cnt":0, "waitresp_msg_cnt":0, "tx":325, "txbytes":28178249, "txerrs":0, "txretries":0, "txidle":2100873, "req_timeouts":0, "rx":325, "rxbytes":20266, "rxerrs":0, "rxcorriderrs":0, "rxpartial":0, "rxidle":2092308, "zbuf_grow":0, "buf_grow":0, "wakeups":333, "connects":1, "disconnects":0, "int_latency": { "min":0, "max":0, "avg":0, "sum":0, "stddev": 0, "p50": 0, "p75": 0, "p90": 0, "p95": 0, "p99": 0, "p99_99": 0, "outofrange": 0, "hdrsize": 12400, "cnt":0 }, "outbuf_latency": { "min":0, "max":0, "avg":0, "sum":0, "stddev": 0, "p50": 0, "p75": 0, "p90": 0, "p95": 0, "p99": 0, "p99_99": 0, "outofrange": 0, "hdrsize": 11376, "cnt":0 }, "rtt": { "min":0, "max":0, "avg":0, "sum":0, "stddev": 0, "p50": 0, "p75": 0, "p90": 0, "p95": 0, "p99": 0, "p99_99": 0, "outofrange": 0, "hdrsize": 13424, "cnt":0 }, "throttle": { "min":0, "max":0, "avg":0, "sum":0, "stddev": 0, "p50": 0, "p75": 0, "p90": 0, "p95": 0, "p99": 0, "p99_99": 0, "outofrange": 0, "hdrsize": 17520, "cnt":0 }, "req": { "Produce": 323, "ListOffsets": 0, "Metadata": 1, "FindCoordinator": 0, "SaslHandshake": 0, "ApiVersion": 1, "InitProducerId": 0, "AddPartitionsToTxn": 0, "AddOffsetsToTxn": 0, "EndTxn": 0, "TxnOffsetCommit": 0, "SaslAuthenticate": 0, "OffsetDeleteRequest": 0, "DescribeClientQuotasRequest": 0, "AlterClientQuotasRequest": 0, "DescribeUserScramCredentialsRequest": 0 }, "toppars":{ "benchmark-0": { "topic":"benchmark", "partition":0} } } }, "topics":{ "benchmark": { "topic":"benchmark", "age":6000, "metadata_age":5897, "batchsize": { "min":0, "max":0, "avg":0, "sum":0, "stddev": 0, "p50": 0, "p75": 0, "p90": 0, "p95": 0, "p99": 0, "p99_99": 0, "outofrange": 0, "hdrsize": 14448, "cnt":0 }, "batchcnt": { "min":0, "max":0, "avg":0, "sum":0, "stddev": 0, "p50": 0, "p75": 0, "p90": 0, "p95": 0, "p99": 0, "p99_99": 0, "outofrange": 0, "hdrsize": 8304, "cnt":0 }, "partitions":{ "0": { "partition":0, "broker":0, "leader":0, "desired":false, "unknown":false, "msgq_cnt":0, "msgq_bytes":0, "xmit_msgq_cnt":0, "xmit_msgq_bytes":0, "fetchq_cnt":0, "fetchq_size":0, "fetch_state":"none", "query_offset":-1001, "next_offset":0, "app_offset":-1001, "stored_offset":-1001, "commited_offset":-1001, "committed_offset":-1001, "eof_offset":-1001, "lo_offset":-1001, "hi_offset":-1001, "ls_offset":-1001, "consumer_lag":-1, "consumer_lag_stored":-1, "txmsgs":3201429, "txbytes":25611432, "rxmsgs":0, "rxbytes":0, "msgs": 3201429, "rx_ver_drops": 0, "msgs_inflight": 0, "next_ack_seq": 0, "next_err_seq": 0, "acked_msgid": 0} , "-1": { "partition":-1, "broker":-1, "leader":-1, "desired":false, "unknown":false, "msgq_cnt":0, "msgq_bytes":0, "xmit_msgq_cnt":0, "xmit_msgq_bytes":0, "fetchq_cnt":0, "fetchq_size":0, "fetch_state":"none", "query_offset":-1001, "next_offset":0, "app_offset":-1001, "stored_offset":-1001, "commited_offset":-1001, "committed_offset":-1001, "eof_offset":-1001, "lo_offset":-1001, "hi_offset":-1001, "ls_offset":-1001, "consumer_lag":-1, "consumer_lag_stored":-1, "txmsgs":0, "txbytes":0, "rxmsgs":0, "rxbytes":0, "msgs": 100000, "rx_ver_drops": 0, "msgs_inflight": 0, "next_ack_seq": 0, "next_err_seq": 0, "acked_msgid": 0} } } } , "tx":325, "tx_bytes":28178249, "rx":325, "rx_bytes":20266, "txmsgs":3201429, "txmsg_bytes":25611432, "rxmsgs":0, "rxmsg_bytes":0}
{ "name": "rdkafka#producer-37", "client_id": "rdkafka", "type": "producer", "ts":13386527110, "time":1682592792, "age":8001161, "replyq":2, "msg_cnt":0, "msg_size":0, "msg_max":100000, "msg_size_max":1073741824, "simple_cnt":0, "metadata_cache_cnt":1, "brokers":{ "192.168.0.131:9092/0": { "name":"192.168.0.131:9092/0", "nodeid":0, "nodename":"192.168.0.131:9092", "source":"configured", "state":"UP", "stateage":7898023, "outbuf_cnt":0, "outbuf_msg_cnt":0, "waitresp_cnt":0, "waitresp_msg_cnt":0, "tx":325, "txbytes":28178249, "txerrs":0, "txretries":0, "txidle":4100916, "req_timeouts":0, "rx":325, "rxbytes":20266, "rxerrs":0, "rxcorriderrs":0, "rxpartial":0, "rxidle":4092351, "zbuf_grow":0, "buf_grow":0, "wakeups":333, "connects":1, "disconnects":0, "int_latency": { "min":0, "max":0, "avg":0, "sum":0, "stddev": 0, "p50": 0, "p75": 0, "p90": 0, "p95": 0, "p99": 0, "p99_99": 0, "outofrange": 0, "hdrsize": 12400, "cnt":0 }, "outbuf_latency": { "min":0, "max":0, "avg":0, "sum":0, "stddev": 0, "p50": 0, "p75": 0, "p90": 0, "p95": 0, "p99": 0, "p99_99": 0, "outofrange": 0, "hdrsize": 11376, "cnt":0 }, "rtt": { "min":0, "max":0, "avg":0, "sum":0, "stddev": 0, "p50": 0, "p75": 0, "p90": 0, "p95": 0, "p99": 0, "p99_99": 0, "outofrange": 0, "hdrsize": 13424, "cnt":0 }, "throttle": { "min":0, "max":0, "avg":0, "sum":0, "stddev": 0, "p50": 0, "p75": 0, "p90": 0, "p95": 0, "p99": 0, "p99_99": 0, "outofrange": 0, "hdrsize": 17520, "cnt":0 }, "req": { "Produce": 323, "ListOffsets": 0, "Metadata": 1, "FindCoordinator": 0, "SaslHandshake": 0, "ApiVersion": 1, "InitProducerId": 0, "AddPartitionsToTxn": 0, "AddOffsetsToTxn": 0, "EndTxn": 0, "TxnOffsetCommit": 0, "SaslAuthenticate": 0, "OffsetDeleteRequest": 0, "DescribeClientQuotasRequest": 0, "AlterClientQuotasRequest": 0, "DescribeUserScramCredentialsRequest": 0 }, "toppars":{ "benchmark-0": { "topic":"benchmark", "partition":0} } } }, "topics":{ "benchmark": { "topic":"benchmark", "age":8000, "metadata_age":7898, "batchsize": { "min":0, "max":0, "avg":0, "sum":0, "stddev": 0, "p50": 0, "p75": 0, "p90": 0, "p95": 0, "p99": 0, "p99_99": 0, "outofrange": 0, "hdrsize": 14448, "cnt":0 }, "batchcnt": { "min":0, "max":0, "avg":0, "sum":0, "stddev": 0, "p50": 0, "p75": 0, "p90": 0, "p95": 0, "p99": 0, "p99_99": 0, "outofrange": 0, "hdrsize": 8304, "cnt":0 }, "partitions":{ "0": { "partition":0, "broker":0, "leader":0, "desired":false, "unknown":false, "msgq_cnt":0, "msgq_bytes":0, "xmit_msgq_cnt":0, "xmit_msgq_bytes":0, "fetchq_cnt":0, "fetchq_size":0, "fetch_state":"none", "query_offset":-1001, "next_offset":0, "app_offset":-1001, "stored_offset":-1001, "commited_offset":-1001, "committed_offset":-1001, "eof_offset":-1001, "lo_offset":-1001, "hi_offset":-1001, "ls_offset":-1001, "consumer_lag":-1, "consumer_lag_stored":-1, "txmsgs":3201429, "txbytes":25611432, "rxmsgs":0, "rxbytes":0, "msgs": 3201429, "rx_ver_drops": 0, "msgs_inflight": 0, "next_ack_seq": 0, "next_err_seq": 0, "acked_msgid": 0} , "-1": { "partition":-1, "broker":-1, "leader":-1, "desired":false, "unknown":false, "msgq_cnt":0, "msgq_bytes":0, "xmit_msgq_cnt":0, "xmit_msgq_bytes":0, "fetchq_cnt":0, "fetchq_size":0, "fetch_state":"none", "query_offset":-1001, "next_offset":0, "app_offset":-1001, "stored_offset":-1001, "commited_offset":-1001, "committed_offset":-1001, "eof_offset":-1001, "lo_offset":-1001, "hi_offset":-1001, "ls_offset":-1001, "consumer_lag":-1, "consumer_lag_stored":-1, "txmsgs":0, "txbytes":0, "rxmsgs":0, "rxbytes":0, "msgs": 100000, "rx_ver_drops": 0, "msgs_inflight": 0, "next_ack_seq": 0, "next_err_seq": 0, "acked_msgid": 0} } } } , "tx":325, "tx_bytes":28178249, "rx":325, "rx_bytes":20266, "txmsgs":3201429, "txmsg_bytes":25611432, "rxmsgs":0, "rxmsg_bytes":0}
{ "name": "rdkafka#producer-37", "client_id": "rdkafka", "type": "producer", "ts":13388527152, "time":1682592794, "age":10001203, "replyq":3, "msg_cnt":0, "msg_size":0, "msg_max":100000, "msg_size_max":1073741824, "simple_cnt":0, "metadata_cache_cnt":1, "brokers":{ "192.168.0.131:9092/0": { "name":"192.168.0.131:9092/0", "nodeid":0, "nodename":"192.168.0.131:9092", "source":"configured", "state":"UP", "stateage":9898065, "outbuf_cnt":0, "outbuf_msg_cnt":0, "waitresp_cnt":0, "waitresp_msg_cnt":0, "tx":325, "txbytes":28178249, "txerrs":0, "txretries":0, "txidle":6100958, "req_timeouts":0, "rx":325, "rxbytes":20266, "rxerrs":0, "rxcorriderrs":0, "rxpartial":0, "rxidle":6092393, "zbuf_grow":0, "buf_grow":0, "wakeups":333, "connects":1, "disconnects":0, "int_latency": { "min":0, "max":0, "avg":0, "sum":0, "stddev": 0, "p50": 0, "p75": 0, "p90": 0, "p95": 0, "p99": 0, "p99_99": 0, "outofrange": 0, "hdrsize": 12400, "cnt":0 }, "outbuf_latency": { "min":0, "max":0, "avg":0, "sum":0, "stddev": 0, "p50": 0, "p75": 0, "p90": 0, "p95": 0, "p99": 0, "p99_99": 0, "outofrange": 0, "hdrsize": 11376, "cnt":0 }, "rtt": { "min":0, "max":0, "avg":0, "sum":0, "stddev": 0, "p50": 0, "p75": 0, "p90": 0, "p95": 0, "p99": 0, "p99_99": 0, "outofrange": 0, "hdrsize": 13424, "cnt":0 }, "throttle": { "min":0, "max":0, "avg":0, "sum":0, "stddev": 0, "p50": 0, "p75": 0, "p90": 0, "p95": 0, "p99": 0, "p99_99": 0, "outofrange": 0, "hdrsize": 17520, "cnt":0 }, "req": { "Produce": 323, "ListOffsets": 0, "Metadata": 1, "FindCoordinator": 0, "SaslHandshake": 0, "ApiVersion": 1, "InitProducerId": 0, "AddPartitionsToTxn": 0, "AddOffsetsToTxn": 0, "EndTxn": 0, "TxnOffsetCommit": 0, "SaslAuthenticate": 0, "OffsetDeleteRequest": 0, "DescribeClientQuotasRequest": 0, "AlterClientQuotasRequest": 0, "DescribeUserScramCredentialsRequest": 0 }, "toppars":{ "benchmark-0": { "topic":"benchmark", "partition":0} } } }, "topics":{ "benchmark": { "topic":"benchmark", "age":10000, "metadata_age":9898, "batchsize": { "min":0, "max":0, "avg":0, "sum":0, "stddev": 0, "p50": 0, "p75": 0, "p90": 0, "p95": 0, "p99": 0, "p99_99": 0, "outofrange": 0, "hdrsize": 14448, "cnt":0 }, "batchcnt": { "min":0, "max":0, "avg":0, "sum":0, "stddev": 0, "p50": 0, "p75": 0, "p90": 0, "p95": 0, "p99": 0, "p99_99": 0, "outofrange": 0, "hdrsize": 8304, "cnt":0 }, "partitions":{ "0": { "partition":0, "broker":0, "leader":0, "desired":false, "unknown":false, "msgq_cnt":0, "msgq_bytes":0, "xmit_msgq_cnt":0, "xmit_msgq_bytes":0, "fetchq_cnt":0, "fetchq_size":0, "fetch_state":"none", "query_offset":-1001, "next_offset":0, "app_offset":-1001, "stored_offset":-1001, "commited_offset":-1001, "committed_offset":-1001, "eof_offset":-1001, "lo_offset":-1001, "hi_offset":-1001, "ls_offset":-1001, "consumer_lag":-1, "consumer_lag_stored":-1, "txmsgs":3201429, "txbytes":25611432, "rxmsgs":0, "rxbytes":0, "msgs": 3201429, "rx_ver_drops": 0, "msgs_inflight": 0, "next_ack_seq": 0, "next_err_seq": 0, "acked_msgid": 0} , "-1": { "partition":-1, "broker":-1, "leader":-1, "desired":false, "unknown":false, "msgq_cnt":0, "msgq_bytes":0, "xmit_msgq_cnt":0, "xmit_msgq_bytes":0, "fetchq_cnt":0, "fetchq_size":0, "fetch_state":"none", "query_offset":-1001, "next_offset":0, "app_offset":-1001, "stored_offset":-1001, "commited_offset":-1001, "committed_offset":-1001, "eof_offset":-1001, "lo_offset":-1001, "hi_offset":-1001, "ls_offset":-1001, "consumer_lag":-1, "consumer_lag_stored":-1, "txmsgs":0, "txbytes":0, "rxmsgs":0, "rxbytes":0, "msgs": 100000, "rx_ver_drops": 0, "msgs_inflight": 0, "next_ack_seq": 0, "next_err_seq": 0, "acked_msgid": 0} } } } , "tx":325, "tx_bytes":28178249, "rx":325, "rx_bytes":20266, "txmsgs":3201429, "txmsg_bytes":25611432, "rxmsgs":0, "rxmsg_bytes":0}
{ "name": "rdkafka#producer-37", "client_id": "rdkafka", "type": "producer", "ts":13390527184, "time":1682592796, "age":12001235, "replyq":0, "msg_cnt":100000, "msg_size":800000, "msg_max":100000, "msg_size_max":1073741824, "simple_cnt":0, "metadata_cache_cnt":1, "brokers":{ "192.168.0.131:9092/0": { "name":"192.168.0.131:9092/0", "nodeid":0, "nodename":"192.168.0.131:9092", "source":"configured", "state":"UP", "stateage":11898097, "outbuf_cnt":0, "outbuf_msg_cnt":0, "waitresp_cnt":4, "waitresp_msg_cnt":40000, "tx":330, "txbytes":28605365, "txerrs":0, "txretries":0, "txidle":14494, "req_timeouts":0, "rx":326, "rxbytes":20327, "rxerrs":0, "rxcorriderrs":0, "rxpartial":0, "rxidle":16747, "zbuf_grow":0, "buf_grow":0, "wakeups":1078, "connects":1, "disconnects":0, "int_latency": { "min":6, "max":93565, "avg":43594, "sum":2502513602, "stddev": 33498, "p50": 33791, "p75": 83967, "p90": 90623, "p95": 92159, "p99": 93695, "p99_99": 93695, "outofrange": 0, "hdrsize": 12400, "cnt":57405 }, "outbuf_latency": { "min":15, "max":42024, "avg":9313, "sum":46566, "stddev": 16480, "p50": 60, "p75": 4447, "p90": 42239, "p95": 42239, "p99": 42239, "p99_99": 42239, "outofrange": 0, "hdrsize": 11376, "cnt":5 }, "rtt": { "min":99655, "max":99655, "avg":99655, "sum":99655, "stddev": 0, "p50": 99839, "p75": 99839, "p90": 99839, "p95": 99839, "p99": 99839, "p99_99": 99839, "outofrange": 0, "hdrsize": 13424, "cnt":1 }, "throttle": { "min":0, "max":0, "avg":0, "sum":0, "stddev": 0, "p50": 0, "p75": 0, "p90": 0, "p95": 0, "p99": 0, "p99_99": 0, "outofrange": 0, "hdrsize": 17520, "cnt":0 }, "req": { "Produce": 328, "ListOffsets": 0, "Metadata": 1, "FindCoordinator": 0, "SaslHandshake": 0, "ApiVersion": 1, "InitProducerId": 0, "AddPartitionsToTxn": 0, "AddOffsetsToTxn": 0, "EndTxn": 0, "TxnOffsetCommit": 0, "SaslAuthenticate": 0, "OffsetDeleteRequest": 0, "DescribeClientQuotasRequest": 0, "AlterClientQuotasRequest": 0, "DescribeUserScramCredentialsRequest": 0 }, "toppars":{ "benchmark-0": { "topic":"benchmark", "partition":0} } } }, "topics":{ "benchmark": { "topic":"benchmark", "age":12000, "metadata_age":11898, "batchsize": { "min":66592, "max":90206, "avg":85367, "sum":426836, "stddev": 9321, "p50": 90111, "p75": 90623, "p90": 90623, "p95": 90623, "p99": 90623, "p99_99": 90623, "outofrange": 0, "hdrsize": 14448, "cnt":5 }, "batchcnt": { "min":7405, "max":10000, "avg":9481, "sum":47405, "stddev": 1043, "p50": 10047, "p75": 10047, "p90": 10047, "p95": 10047, "p99": 10047, "p99_99": 10047, "outofrange": 0, "hdrsize": 8304, "cnt":5 }, "partitions":{ "0": { "partition":0, "broker":0, "leader":0, "desired":false, "unknown":false, "msgq_cnt":3953, "msgq_bytes":31624, "xmit_msgq_cnt":0, "xmit_msgq_bytes":0, "fetchq_cnt":0, "fetchq_size":0, "fetch_state":"none", "query_offset":-1001, "next_offset":0, "app_offset":-1001, "stored_offset":-1001, "commited_offset":-1001, "committed_offset":-1001, "eof_offset":-1001, "lo_offset":-1001, "hi_offset":-1001, "ls_offset":-1001, "consumer_lag":-1, "consumer_lag_stored":-1, "txmsgs":3258834, "txbytes":26070672, "rxmsgs":0, "rxbytes":0, "msgs": 3308834, "rx_ver_drops": 0, "msgs_inflight": 40000, "next_ack_seq": 0, "next_err_seq": 0, "acked_msgid": 0} , "-1": { "partition":-1, "broker":-1, "leader":-1, "desired":false, "unknown":false, "msgq_cnt":0, "msgq_bytes":0, "xmit_msgq_cnt":0, "xmit_msgq_bytes":0, "fetchq_cnt":0, "fetchq_size":0, "fetch_state":"none", "query_offset":-1001, "next_offset":0, "app_offset":-1001, "stored_offset":-1001, "commited_offset":-1001, "committed_offset":-1001, "eof_offset":-1001, "lo_offset":-1001, "hi_offset":-1001, "ls_offset":-1001, "consumer_lag":-1, "consumer_lag_stored":-1, "txmsgs":0, "txbytes":0, "rxmsgs":0, "rxbytes":0, "msgs": 100000, "rx_ver_drops": 0, "msgs_inflight": 0, "next_ack_seq": 0, "next_err_seq": 0, "acked_msgid": 0} } } } , "tx":330, "tx_bytes":28605365, "rx":326, "rx_bytes":20327, "txmsgs":3258834, "txmsg_bytes":26070672, "rxmsgs":0, "rxmsg_bytes":0}
{ "name": "rdkafka#producer-37", "client_id": "rdkafka", "type": "producer", "ts":13392527516, "time":1682592798, "age":14001567, "replyq":0, "msg_cnt":92299, "msg_size":738392, "msg_max":100000, "msg_size_max":1073741824, "simple_cnt":0, "metadata_cache_cnt":1, "brokers":{ "192.168.0.131:9092/0": { "name":"192.168.0.131:9092/0", "nodeid":0, "nodename":"192.168.0.131:9092", "source":"configured", "state":"UP", "stateage":13898429, "outbuf_cnt":1, "outbuf_msg_cnt":10000, "waitresp_cnt":0, "waitresp_msg_cnt":0, "tx":504, "txbytes":43954566, "txerrs":0, "txretries":0, "txidle":11668, "req_timeouts":0, "rx":504, "rxbytes":31185, "rxerrs":0, "rxcorriderrs":0, "rxpartial":0, "rxidle":796, "zbuf_grow":0, "buf_grow":0, "wakeups":1253, "connects":1, "disconnects":0, "int_latency": { "min":56941, "max":152591, "avg":83880, "sum":145951514251, "stddev": 10070, "p50": 82943, "p75": 87551, "p90": 92671, "p95": 95743, "p99": 139263, "p99_99": 152575, "outofrange": 0, "hdrsize": 12400, "cnt":1740000 }, "outbuf_latency": { "min":10, "max":12577, "avg":2599, "sum":452310, "stddev": 2536, "p50": 2415, "p75": 4991, "p90": 5407, "p95": 5727, "p99": 6751, "p99_99": 12607, "outofrange": 0, "hdrsize": 11376, "cnt":174 }, "rtt": { "min":9482, "max":98811, "avg":16152, "sum":2875185, "stddev": 9523, "p50": 17023, "p75": 17663, "p90": 19455, "p95": 26879, "p99": 36607, "p99_99": 98815, "outofrange": 0, "hdrsize": 13424, "cnt":178 }, "throttle": { "min":0, "max":0, "avg":0, "sum":0, "stddev": 0, "p50": 0, "p75": 0, "p90": 0, "p95": 0, "p99": 0, "p99_99": 0, "outofrange": 0, "hdrsize": 17520, "cnt":0 }, "req": { "Produce": 502, "ListOffsets": 0, "Metadata": 1, "FindCoordinator": 0, "SaslHandshake": 0, "ApiVersion": 1, "InitProducerId": 0, "AddPartitionsToTxn": 0, "AddOffsetsToTxn": 0, "EndTxn": 0, "TxnOffsetCommit": 0, "SaslAuthenticate": 0, "OffsetDeleteRequest": 0, "DescribeClientQuotasRequest": 0, "AlterClientQuotasRequest": 0, "DescribeUserScramCredentialsRequest": 0 }, "toppars":{ "benchmark-0": { "topic":"benchmark", "partition":0} } } }, "topics":{ "benchmark": { "topic":"benchmark", "age":14000, "metadata_age":13898, "batchsize": { "min":84905, "max":90539, "avg":88168, "sum":15429571, "stddev": 1144, "p50": 88575, "p75": 89087, "p90": 89599, "p95": 90111, "p99": 90111, "p99_99": 90623, "outofrange": 0, "hdrsize": 14448, "cnt":175 }, "batchcnt": { "min":10000, "max":10000, "avg":10000, "sum":1750000, "stddev": 0, "p50": 10047, "p75": 10047, "p90": 10047, "p95": 10047, "p99": 10047, "p99_99": 10047, "outofrange": 0, "hdrsize": 8304, "cnt":175 }, "partitions":{ "0": { "partition":0, "broker":0, "leader":0, "desired":false, "unknown":false, "msgq_cnt":0, "msgq_bytes":0, "xmit_msgq_cnt":0, "xmit_msgq_bytes":0, "fetchq_cnt":0, "fetchq_size":0, "fetch_state":"none", "query_offset":-1001, "next_offset":0, "app_offset":-1001, "stored_offset":-1001, "commited_offset":-1001, "committed_offset":-1001, "eof_offset":-1001, "lo_offset":-1001, "hi_offset":-1001, "ls_offset":-1001, "consumer_lag":-1, "consumer_lag_stored":-1, "txmsgs":4998834, "txbytes":39990672, "rxmsgs":0, "rxbytes":0, "msgs": 5073478, "rx_ver_drops": 0, "msgs_inflight": 10000, "next_ack_seq": 0, "next_err_seq": 0, "acked_msgid": 0} , "-1": { "partition":-1, "broker":-1, "leader":-1, "desired":false, "unknown":false, "msgq_cnt":0, "msgq_bytes":0, "xmit_msgq_cnt":0, "xmit_msgq_bytes":0, "fetchq_cnt":0, "fetchq_size":0, "fetch_state":"none", "query_offset":-1001, "next_offset":0, "app_offset":-1001, "stored_offset":-1001, "commited_offset":-1001, "committed_offset":-1001, "eof_offset":-1001, "lo_offset":-1001, "hi_offset":-1001, "ls_offset":-1001, "consumer_lag":-1, "consumer_lag_stored":-1, "txmsgs":0, "txbytes":0, "rxmsgs":0, "rxbytes":0, "msgs": 100000, "rx_ver_drops": 0, "msgs_inflight": 0, "next_ack_seq": 0, "next_err_seq": 0, "acked_msgid": 0} } } } , "tx":504, "tx_bytes":43954566, "rx":504, "rx_bytes":31185, "txmsgs":4998834, "txmsg_bytes":39990672, "rxmsgs":0, "rxmsg_bytes":0}
{ "name": "rdkafka#producer-37", "client_id": "rdkafka", "type": "producer", "ts":13394528020, "time":1682592800, "age":16002071, "replyq":0, "msg_cnt":0, "msg_size":0, "msg_max":100000, "msg_size_max":1073741824, "simple_cnt":0, "metadata_cache_cnt":1, "brokers":{ "192.168.0.131:9092/0": { "name":"192.168.0.131:9092/0", "nodeid":0, "nodename":"192.168.0.131:9092", "source":"configured", "state":"UP", "stateage":15898933, "outbuf_cnt":0, "outbuf_msg_cnt":0, "waitresp_cnt":0, "waitresp_msg_cnt":0, "tx":663, "txbytes":57861708, "txerrs":0, "txretries":0, "txidle":243750, "req_timeouts":0, "rx":663, "rxbytes":40884, "rxerrs":0, "rxcorriderrs":0, "rxpartial":0, "rxidle":235411, "zbuf_grow":0, "buf_grow":0, "wakeups":1413, "connects":1, "disconnects":0, "int_latency": { "min":9867, "max":112324, "avg":80180, "sum":126322720618, "stddev": 15167, "p50": 80895, "p75": 87039, "p90": 99327, "p95": 103935, "p99": 108543, "p99_99": 112639, "outofrange": 0, "hdrsize": 12400, "cnt":1575487 }, "outbuf_latency": { "min":13, "max":6361, "avg":2328, "sum":370259, "stddev": 2085, "p50": 2447, "p75": 4607, "p90": 4927, "p95": 5087, "p99": 6047, "p99_99": 6367, "outofrange": 0, "hdrsize": 11376, "cnt":159 }, "rtt": { "min":8339, "max":39407, "avg":15105, "sum":2401699, "stddev": 5400, "p50": 15103, "p75": 17535, "p90": 19839, "p95": 22527, "p99": 33791, "p99_99": 39423, "outofrange": 0, "hdrsize": 13424, "cnt":159 }, "throttle": { "min":0, "max":0, "avg":0, "sum":0, "stddev": 0, "p50": 0, "p75": 0, "p90": 0, "p95": 0, "p99": 0, "p99_99": 0, "outofrange": 0, "hdrsize": 17520, "cnt":0 }, "req": { "Produce": 661, "ListOffsets": 0, "Metadata": 1, "FindCoordinator": 0, "SaslHandshake": 0, "ApiVersion": 1, "InitProducerId": 0, "AddPartitionsToTxn": 0, "AddOffsetsToTxn": 0, "EndTxn": 0, "TxnOffsetCommit": 0, "SaslAuthenticate": 0, "OffsetDeleteRequest": 0, "DescribeClientQuotasRequest": 0, "AlterClientQuotasRequest": 0, "DescribeUserScramCredentialsRequest": 0 }, "toppars":{ "benchmark-0": { "topic":"benchmark", "partition":0} } } }, "topics":{ "benchmark": { "topic":"benchmark", "age":16001, "metadata_age":15898, "batchsize": { "min":44217, "max":90802, "avg":87393, "sum":13808124, "stddev": 4172, "p50": 88575, "p75": 89599, "p90": 90111, "p95": 90111, "p99": 90623, "p99_99": 91135, "outofrange": 0, "hdrsize": 14448, "cnt":158 }, "batchcnt": { "min":5487, "max":10000, "avg":9971, "sum":1575487, "stddev": 359, "p50": 10047, "p75": 10047, "p90": 10047, "p95": 10047, "p99": 10047, "p99_99": 10047, "outofrange": 0, "hdrsize": 8304, "cnt":158 }, "partitions":{ "0": { "partition":0, "broker":0, "leader":0, "desired":false, "unknown":false, "msgq_cnt":0, "msgq_bytes":0, "xmit_msgq_cnt":0, "xmit_msgq_bytes":0, "fetchq_cnt":0, "fetchq_size":0, "fetch_state":"none", "query_offset":-1001, "next_offset":0, "app_offset":-1001, "stored_offset":-1001, "commited_offset":-1001, "committed_offset":-1001, "eof_offset":-1001, "lo_offset":-1001, "hi_offset":-1001, "ls_offset":-1001, "consumer_lag":-1, "consumer_lag_stored":-1, "txmsgs":6574321, "txbytes":52594568, "rxmsgs":0, "rxbytes":0, "msgs": 6574321, "rx_ver_drops": 0, "msgs_inflight": 0, "next_ack_seq": 0, "next_err_seq": 0, "acked_msgid": 0} , "-1": { "partition":-1, "broker":-1, "leader":-1, "desired":false, "unknown":false, "msgq_cnt":0, "msgq_bytes":0, "xmit_msgq_cnt":0, "xmit_msgq_bytes":0, "fetchq_cnt":0, "fetchq_size":0, "fetch_state":"none", "query_offset":-1001, "next_offset":0, "app_offset":-1001, "stored_offset":-1001, "commited_offset":-1001, "committed_offset":-1001, "eof_offset":-1001, "lo_offset":-1001, "hi_offset":-1001, "ls_offset":-1001, "consumer_lag":-1, "consumer_lag_stored":-1, "txmsgs":0, "txbytes":0, "rxmsgs":0, "rxbytes":0, "msgs": 100000, "rx_ver_drops": 0, "msgs_inflight": 0, "next_ack_seq": 0, "next_err_seq": 0, "acked_msgid": 0} } } } , "tx":663, "tx_bytes":57861708, "rx":663, "rx_bytes":40884, "txmsgs":6574321, "txmsg_bytes":52594568, "rxmsgs":0, "rxmsg_bytes":0}
{ "name": "rdkafka#producer-37", "client_id": "rdkafka", "type": "producer", "ts":13396528611, "time":1682592802, "age":18002662, "replyq":1, "msg_cnt":0, "msg_size":0, "msg_max":100000, "msg_size_max":1073741824, "simple_cnt":0, "metadata_cache_cnt":1, "brokers":{ "192.168.0.131:9092/0": { "name":"192.168.0.131:9092/0", "nodeid":0, "nodename":"192.168.0.131:9092", "source":"configured", "state":"UP", "stateage":17899524, "outbuf_cnt":0, "outbuf_msg_cnt":0, "waitresp_cnt":0, "waitresp_msg_cnt":0, "tx":663, "txbytes":57861708, "txerrs":0, "txretries":0, "txidle":2244341, "req_timeouts":0, "rx":663, "rxbytes":40884, "rxerrs":0, "rxcorriderrs":0, "rxpartial":0, "rxidle":2236002, "zbuf_grow":0, "buf_grow":0, "wakeups":1413, "connects":1, "disconnects":0, "int_latency": { "min":0, "max":0, "avg":0, "sum":0, "stddev": 0, "p50": 0, "p75": 0, "p90": 0, "p95": 0, "p99": 0, "p99_99": 0, "outofrange": 0, "hdrsize": 12400, "cnt":0 }, "outbuf_latency": { "min":0, "max":0, "avg":0, "sum":0, "stddev": 0, "p50": 0, "p75": 0, "p90": 0, "p95": 0, "p99": 0, "p99_99": 0, "outofrange": 0, "hdrsize": 11376, "cnt":0 }, "rtt": { "min":0, "max":0, "avg":0, "sum":0, "stddev": 0, "p50": 0, "p75": 0, "p90": 0, "p95": 0, "p99": 0, "p99_99": 0, "outofrange": 0, "hdrsize": 13424, "cnt":0 }, "throttle": { "min":0, "max":0, "avg":0, "sum":0, "stddev": 0, "p50": 0, "p75": 0, "p90": 0, "p95": 0, "p99": 0, "p99_99": 0, "outofrange": 0, "hdrsize": 17520, "cnt":0 }, "req": { "Produce": 661, "ListOffsets": 0, "Metadata": 1, "FindCoordinator": 0, "SaslHandshake": 0, "ApiVersion": 1, "InitProducerId": 0, "AddPartitionsToTxn": 0, "AddOffsetsToTxn": 0, "EndTxn": 0, "TxnOffsetCommit": 0, "SaslAuthenticate": 0, "OffsetDeleteRequest": 0, "DescribeClientQuotasRequest": 0, "AlterClientQuotasRequest": 0, "DescribeUserScramCredentialsRequest": 0 }, "toppars":{ "benchmark-0": { "topic":"benchmark", "partition":0} } } }, "topics":{ "benchmark": { "topic":"benchmark", "age":18001, "metadata_age":17899, "batchsize": { "min":0, "max":0, "avg":0, "sum":0, "stddev": 0, "p50": 0, "p75": 0, "p90": 0, "p95": 0, "p99": 0, "p99_99": 0, "outofrange": 0, "hdrsize": 14448, "cnt":0 }, "batchcnt": { "min":0, "max":0, "avg":0, "sum":0, "stddev": 0, "p50": 0, "p75": 0, "p90": 0, "p95": 0, "p99": 0, "p99_99": 0, "outofrange": 0, "hdrsize": 8304, "cnt":0 }, "partitions":{ "0": { "partition":0, "broker":0, "leader":0, "desired":false, "unknown":false, "msgq_cnt":0, "msgq_bytes":0, "xmit_msgq_cnt":0, "xmit_msgq_bytes":0, "fetchq_cnt":0, "fetchq_size":0, "fetch_state":"none", "query_offset":-1001, "next_offset":0, "app_offset":-1001, "stored_offset":-1001, "commited_offset":-1001, "committed_offset":-1001, "eof_offset":-1001, "lo_offset":-1001, "hi_offset":-1001, "ls_offset":-1001, "consumer_lag":-1, "consumer_lag_stored":-1, "txmsgs":6574321, "txbytes":52594568, "rxmsgs":0, "rxbytes":0, "msgs": 6574321, "rx_ver_drops": 0, "msgs_inflight": 0, "next_ack_seq": 0, "next_err_seq": 0, "acked_msgid": 0} , "-1": { "partition":-1, "broker":-1, "leader":-1, "desired":false, "unknown":false, "msgq_cnt":0, "msgq_bytes":0, "xmit_msgq_cnt":0, "xmit_msgq_bytes":0, "fetchq_cnt":0, "fetchq_size":0, "fetch_state":"none", "query_offset":-1001, "next_offset":0, "app_offset":-1001, "stored_offset":-1001, "commited_offset":-1001, "committed_offset":-1001, "eof_offset":-1001, "lo_offset":-1001, "hi_offset":-1001, "ls_offset":-1001, "consumer_lag":-1, "consumer_lag_stored":-1, "txmsgs":0, "txbytes":0, "rxmsgs":0, "rxbytes":0, "msgs": 100000, "rx_ver_drops": 0, "msgs_inflight": 0, "next_ack_seq": 0, "next_err_seq": 0, "acked_msgid": 0} } } } , "tx":663, "tx_bytes":57861708, "rx":663, "rx_bytes":40884, "txmsgs":6574321, "txmsg_bytes":52594568, "rxmsgs":0, "rxmsg_bytes":0}
{ "name": "rdkafka#producer-37", "client_id": "rdkafka", "type": "producer", "ts":13398528632, "time":1682592804, "age":20002683, "replyq":2, "msg_cnt":0, "msg_size":0, "msg_max":100000, "msg_size_max":1073741824, "simple_cnt":0, "metadata_cache_cnt":1, "brokers":{ "192.168.0.131:9092/0": { "name":"192.168.0.131:9092/0", "nodeid":0, "nodename":"192.168.0.131:9092", "source":"configured", "state":"UP", "stateage":19899545, "outbuf_cnt":0, "outbuf_msg_cnt":0, "waitresp_cnt":0, "waitresp_msg_cnt":0, "tx":663, "txbytes":57861708, "txerrs":0, "txretries":0, "txidle":4244362, "req_timeouts":0, "rx":663, "rxbytes":40884, "rxerrs":0, "rxcorriderrs":0, "rxpartial":0, "rxidle":4236023, "zbuf_grow":0, "buf_grow":0, "wakeups":1413, "connects":1, "disconnects":0, "int_latency": { "min":0, "max":0, "avg":0, "sum":0, "stddev": 0, "p50": 0, "p75": 0, "p90": 0, "p95": 0, "p99": 0, "p99_99": 0, "outofrange": 0, "hdrsize": 12400, "cnt":0 }, "outbuf_latency": { "min":0, "max":0, "avg":0, "sum":0, "stddev": 0, "p50": 0, "p75": 0, "p90": 0, "p95": 0, "p99": 0, "p99_99": 0, "outofrange": 0, "hdrsize": 11376, "cnt":0 }, "rtt": { "min":0, "max":0, "avg":0, "sum":0, "stddev": 0, "p50": 0, "p75": 0, "p90": 0, "p95": 0, "p99": 0, "p99_99": 0, "outofrange": 0, "hdrsize": 13424, "cnt":0 }, "throttle": { "min":0, "max":0, "avg":0, "sum":0, "stddev": 0, "p50": 0, "p75": 0, "p90": 0, "p95": 0, "p99": 0, "p99_99": 0, "outofrange": 0, "hdrsize": 17520, "cnt":0 }, "req": { "Produce": 661, "ListOffsets": 0, "Metadata": 1, "FindCoordinator": 0, "SaslHandshake": 0, "ApiVersion": 1, "InitProducerId": 0, "AddPartitionsToTxn": 0, "AddOffsetsToTxn": 0, "EndTxn": 0, "TxnOffsetCommit": 0, "SaslAuthenticate": 0, "OffsetDeleteRequest": 0, "DescribeClientQuotasRequest": 0, "AlterClientQuotasRequest": 0, "DescribeUserScramCredentialsRequest": 0 }, "toppars":{ "benchmark-0": { "topic":"benchmark", "partition":0} } } }, "topics":{ "benchmark": { "topic":"benchmark", "age":20001, "metadata_age":19899, "batchsize": { "min":0, "max":0, "avg":0, "sum":0, "stddev": 0, "p50": 0, "p75": 0, "p90": 0, "p95": 0, "p99": 0, "p99_99": 0, "outofrange": 0, "hdrsize": 14448, "cnt":0 }, "batchcnt": { "min":0, "max":0, "avg":0, "sum":0, "stddev": 0, "p50": 0, "p75": 0, "p90": 0, "p95": 0, "p99": 0, "p99_99": 0, "outofrange": 0, "hdrsize": 8304, "cnt":0 }, "partitions":{ "0": { "partition":0, "broker":0, "leader":0, "desired":false, "unknown":false, "msgq_cnt":0, "msgq_bytes":0, "xmit_msgq_cnt":0, "xmit_msgq_bytes":0, "fetchq_cnt":0, "fetchq_size":0, "fetch_state":"none", "query_offset":-1001, "next_offset":0, "app_offset":-1001, "stored_offset":-1001, "commited_offset":-1001, "committed_offset":-1001, "eof_offset":-1001, "lo_offset":-1001, "hi_offset":-1001, "ls_offset":-1001, "consumer_lag":-1, "consumer_lag_stored":-1, "txmsgs":6574321, "txbytes":52594568, "rxmsgs":0, "rxbytes":0, "msgs": 6574321, "rx_ver_drops": 0, "msgs_inflight": 0, "next_ack_seq": 0, "next_err_seq": 0, "acked_msgid": 0} , "-1": { "partition":-1, "broker":-1, "leader":-1, "desired":false, "unknown":false, "msgq_cnt":0, "msgq_bytes":0, "xmit_msgq_cnt":0, "xmit_msgq_bytes":0, "fetchq_cnt":0, "fetchq_size":0, "fetch_state":"none", "query_offset":-1001, "next_offset":0, "app_offset":-1001, "stored_offset":-1001, "commited_offset":-1001, "committed_offset":-1001, "eof_offset":-1001, "lo_offset":-1001, "hi_offset":-1001, "ls_offset":-1001, "consumer_lag":-1, "consumer_lag_stored":-1, "txmsgs":0, "txbytes":0, "rxmsgs":0, "rxbytes":0, "msgs": 100000, "rx_ver_drops": 0, "msgs_inflight": 0, "next_ack_seq": 0, "next_err_seq": 0, "acked_msgid": 0} } } } , "tx":663, "tx_bytes":57861708, "rx":663, "rx_bytes":40884, "txmsgs":6574321, "txmsg_bytes":52594568, "rxmsgs":0, "rxmsg_bytes":0}
{ "name": "rdkafka#producer-37", "client_id": "rdkafka", "type": "producer", "ts":13400528667, "time":1682592806, "age":22002718, "replyq":3, "msg_cnt":0, "msg_size":0, "msg_max":100000, "msg_size_max":1073741824, "simple_cnt":0, "metadata_cache_cnt":1, "brokers":{ "192.168.0.131:9092/0": { "name":"192.168.0.131:9092/0", "nodeid":0, "nodename":"192.168.0.131:9092", "source":"configured", "state":"UP", "stateage":21899580, "outbuf_cnt":0, "outbuf_msg_cnt":0, "waitresp_cnt":0, "waitresp_msg_cnt":0, "tx":663, "txbytes":57861708, "txerrs":0, "txretries":0, "txidle":6244397, "req_timeouts":0, "rx":663, "rxbytes":40884, "rxerrs":0, "rxcorriderrs":0, "rxpartial":0, "rxidle":6236058, "zbuf_grow":0, "buf_grow":0, "wakeups":1413, "connects":1, "disconnects":0, "int_latency": { "min":0, "max":0, "avg":0, "sum":0, "stddev": 0, "p50": 0, "p75": 0, "p90": 0, "p95": 0, "p99": 0, "p99_99": 0, "outofrange": 0, "hdrsize": 12400, "cnt":0 }, "outbuf_latency": { "min":0, "max":0, "avg":0, "sum":0, "stddev": 0, "p50": 0, "p75": 0, "p90": 0, "p95": 0, "p99": 0, "p99_99": 0, "outofrange": 0, "hdrsize": 11376, "cnt":0 }, "rtt": { "min":0, "max":0, "avg":0, "sum":0, "stddev": 0, "p50": 0, "p75": 0, "p90": 0, "p95": 0, "p99": 0, "p99_99": 0, "outofrange": 0, "hdrsize": 13424, "cnt":0 }, "throttle": { "min":0, "max":0, "avg":0, "sum":0, "stddev": 0, "p50": 0, "p75": 0, "p90": 0, "p95": 0, "p99": 0, "p99_99": 0, "outofrange": 0, "hdrsize": 17520, "cnt":0 }, "req": { "Produce": 661, "ListOffsets": 0, "Metadata": 1, "FindCoordinator": 0, "SaslHandshake": 0, "ApiVersion": 1, "InitProducerId": 0, "AddPartitionsToTxn": 0, "AddOffsetsToTxn": 0, "EndTxn": 0, "TxnOffsetCommit": 0, "SaslAuthenticate": 0, "OffsetDeleteRequest": 0, "DescribeClientQuotasRequest": 0, "AlterClientQuotasRequest": 0, "DescribeUserScramCredentialsRequest": 0 }, "toppars":{ "benchmark-0": { "topic":"benchmark", "partition":0} } } }, "topics":{ "benchmark": { "topic":"benchmark", "age":22001, "metadata_age":21899, "batchsize": { "min":0, "max":0, "avg":0, "sum":0, "stddev": 0, "p50": 0, "p75": 0, "p90": 0, "p95": 0, "p99": 0, "p99_99": 0, "outofrange": 0, "hdrsize": 14448, "cnt":0 }, "batchcnt": { "min":0, "max":0, "avg":0, "sum":0, "stddev": 0, "p50": 0, "p75": 0, "p90": 0, "p95": 0, "p99": 0, "p99_99": 0, "outofrange": 0, "hdrsize": 8304, "cnt":0 }, "partitions":{ "0": { "partition":0, "broker":0, "leader":0, "desired":false, "unknown":false, "msgq_cnt":0, "msgq_bytes":0, "xmit_msgq_cnt":0, "xmit_msgq_bytes":0, "fetchq_cnt":0, "fetchq_size":0, "fetch_state":"none", "query_offset":-1001, "next_offset":0, "app_offset":-1001, "stored_offset":-1001, "commited_offset":-1001, "committed_offset":-1001, "eof_offset":-1001, "lo_offset":-1001, "hi_offset":-1001, "ls_offset":-1001, "consumer_lag":-1, "consumer_lag_stored":-1, "txmsgs":6574321, "txbytes":52594568, "rxmsgs":0, "rxbytes":0, "msgs": 6574321, "rx_ver_drops": 0, "msgs_inflight": 0, "next_ack_seq": 0, "next_err_seq": 0, "acked_msgid": 0} , "-1": { "partition":-1, "broker":-1, "leader":-1, "desired":false, "unknown":false, "msgq_cnt":0, "msgq_bytes":0, "xmit_msgq_cnt":0, "xmit_msgq_bytes":0, "fetchq_cnt":0, "fetchq_size":0, "fetch_state":"none", "query_offset":-1001, "next_offset":0, "app_offset":-1001, "stored_offset":-1001, "commited_offset":-1001, "committed_offset":-1001, "eof_offset":-1001, "lo_offset":-1001, "hi_offset":-1001, "ls_offset":-1001, "consumer_lag":-1, "consumer_lag_stored":-1, "txmsgs":0, "txbytes":0, "rxmsgs":0, "rxbytes":0, "msgs": 100000, "rx_ver_drops": 0, "msgs_inflight": 0, "next_ack_seq": 0, "next_err_seq": 0, "acked_msgid": 0} } } } , "tx":663, "tx_bytes":57861708, "rx":663, "rx_bytes":40884, "txmsgs":6574321, "txmsg_bytes":52594568, "rxmsgs":0, "rxmsg_bytes":0}
{ "name": "rdkafka#producer-37", "client_id": "rdkafka", "type": "producer", "ts":13402528701, "time":1682592808, "age":24002752, "replyq":0, "msg_cnt":100000, "msg_size":800000, "msg_max":100000, "msg_size_max":1073741824, "simple_cnt":0, "metadata_cache_cnt":1, "brokers":{ "192.168.0.131:9092/0": { "name":"192.168.0.131:9092/0", "nodeid":0, "nodename":"192.168.0.131:9092", "source":"configured", "state":"UP", "stateage":23899614, "outbuf_cnt":0, "outbuf_msg_cnt":0, "waitresp_cnt":1, "waitresp_msg_cnt":10000, "tx":679, "txbytes":59271492, "txerrs":0, "txretries":0, "txidle":10578, "req_timeouts":0, "rx":678, "rxbytes":41799, "rxerrs":0, "rxcorriderrs":0, "rxpartial":0, "rxidle":13169, "zbuf_grow":0, "buf_grow":0, "wakeups":2245, "connects":1, "disconnects":0, "int_latency": { "min":19, "max":92560, "avg":50032, "sum":8372663011, "stddev": 20742, "p50": 50175, "p75": 65279, "p90": 74239, "p95": 81919, "p99": 91647, "p99_99": 92671, "outofrange": 0, "hdrsize": 12400, "cnt":167345 }, "outbuf_latency": { "min":14, "max":9362, "avg":2914, "sum":46632, "stddev": 2863, "p50": 2543, "p75": 4671, "p90": 5023, "p95": 8031, "p99": 9407, "p99_99": 9407, "outofrange": 0, "hdrsize": 11376, "cnt":16 }, "rtt": { "min":10857, "max":101586, "avg":51596, "sum":773950, "stddev": 26568, "p50": 56063, "p75": 71167, "p90": 81919, "p95": 81919, "p99": 101887, "p99_99": 101887, "outofrange": 0, "hdrsize": 13424, "cnt":15 }, "throttle": { "min":0, "max":0, "avg":0, "sum":0, "stddev": 0, "p50": 0, "p75": 0, "p90": 0, "p95": 0, "p99": 0, "p99_99": 0, "outofrange": 0, "hdrsize": 17520, "cnt":0 }, "req": { "Produce": 677, "ListOffsets": 0, "Metadata": 1, "FindCoordinator": 0, "SaslHandshake": 0, "ApiVersion": 1, "InitProducerId": 0, "AddPartitionsToTxn": 0, "AddOffsetsToTxn": 0, "EndTxn": 0, "TxnOffsetCommit": 0, "SaslAuthenticate": 0, "OffsetDeleteRequest": 0, "DescribeClientQuotasRequest": 0, "AlterClientQuotasRequest": 0, "DescribeUserScramCredentialsRequest": 0 }, "toppars":{ "benchmark-0": { "topic":"benchmark", "partition":0} } } }, "topics":{ "benchmark": { "topic":"benchmark", "age":24001, "metadata_age":23899, "batchsize": { "min":66031, "max":89971, "avg":88055, "sum":1408888, "stddev": 5758, "p50": 89599, "p75": 90111, "p90": 90111, "p95": 90111, "p99": 90111, "p99_99": 90111, "outofrange": 0, "hdrsize": 14448, "cnt":16 }, "batchcnt": { "min":7345, "max":10000, "avg":9834, "sum":157345, "stddev": 646, "p50": 10047, "p75": 10047, "p90": 10047, "p95": 10047, "p99": 10047, "p99_99": 10047, "outofrange": 0, "hdrsize": 8304, "cnt":16 }, "partitions":{ "0": { "partition":0, "broker":0, "leader":0, "desired":false, "unknown":false, "msgq_cnt":5685, "msgq_bytes":45480, "xmit_msgq_cnt":0, "xmit_msgq_bytes":0, "fetchq_cnt":0, "fetchq_size":0, "fetch_state":"none", "query_offset":-1001, "next_offset":0, "app_offset":-1001, "stored_offset":-1001, "commited_offset":-1001, "committed_offset":-1001, "eof_offset":-1001, "lo_offset":-1001, "hi_offset":-1001, "ls_offset":-1001, "consumer_lag":-1, "consumer_lag_stored":-1, "txmsgs":6741666, "txbytes":53933328, "rxmsgs":0, "rxbytes":0, "msgs": 6821666, "rx_ver_drops": 0, "msgs_inflight": 10000, "next_ack_seq": 0, "next_err_seq": 0, "acked_msgid": 0} , "-1": { "partition":-1, "broker":-1, "leader":-1, "desired":false, "unknown":false, "msgq_cnt":0, "msgq_bytes":0, "xmit_msgq_cnt":0, "xmit_msgq_bytes":0, "fetchq_cnt":0, "fetchq_size":0, "fetch_state":"none", "query_offset":-1001, "next_offset":0, "app_offset":-1001, "stored_offset":-1001, "commited_offset":-1001, "committed_offset":-1001, "eof_offset":-1001, "lo_offset":-1001, "hi_offset":-1001, "ls_offset":-1001, "consumer_lag":-1, "consumer_lag_stored":-1, "txmsgs":0, "txbytes":0, "rxmsgs":0, "rxbytes":0, "msgs": 100000, "rx_ver_drops": 0, "msgs_inflight": 0, "next_ack_seq": 0, "next_err_seq": 0, "acked_msgid": 0} } } } , "tx":679, "tx_bytes":59271492, "rx":678, "rx_bytes":41799, "txmsgs":6741666, "txmsg_bytes":53933328, "rxmsgs":0, "rxmsg_bytes":0}
{ "name": "rdkafka#producer-37", "client_id": "rdkafka", "type": "producer", "ts":13404529017, "time":1682592810, "age":26003068, "replyq":0, "msg_cnt":100000, "msg_size":800000, "msg_max":100000, "msg_size_max":1073741824, "simple_cnt":0, "metadata_cache_cnt":1, "brokers":{ "192.168.0.131:9092/0": { "name":"192.168.0.131:9092/0", "nodeid":0, "nodename":"192.168.0.131:9092", "source":"configured", "state":"UP", "stateage":25899930, "outbuf_cnt":0, "outbuf_msg_cnt":0, "waitresp_cnt":2, "waitresp_msg_cnt":20000, "tx":840, "txbytes":73503476, "txerrs":0, "txretries":0, "txidle":1675, "req_timeouts":0, "rx":838, "rxbytes":51559, "rxerrs":0, "rxcorriderrs":0, "rxpartial":0, "rxidle":14171, "zbuf_grow":0, "buf_grow":0, "wakeups":2406, "connects":1, "disconnects":0, "int_latency": { "min":70442, "max":111993, "avg":95049, "sum":153029282386, "stddev": 11030, "p50": 93183, "p75": 106495, "p90": 109055, "p95": 110079, "p99": 111103, "p99_99": 112127, "outofrange": 0, "hdrsize": 12400, "cnt":1610000 }, "outbuf_latency": { "min":14, "max":8468, "avg":2678, "sum":431266, "stddev": 2029, "p50": 2671, "p75": 4863, "p90": 5567, "p95": 5663, "p99": 5951, "p99_99": 8511, "outofrange": 0, "hdrsize": 11376, "cnt":161 }, "rtt": { "min":9898, "max":31335, "avg":13339, "sum":2134293, "stddev": 3932, "p50": 11199, "p75": 17407, "p90": 18047, "p95": 20863, "p99": 23935, "p99_99": 31359, "outofrange": 0, "hdrsize": 13424, "cnt":160 }, "throttle": { "min":0, "max":0, "avg":0, "sum":0, "stddev": 0, "p50": 0, "p75": 0, "p90": 0, "p95": 0, "p99": 0, "p99_99": 0, "outofrange": 0, "hdrsize": 17520, "cnt":0 }, "req": { "Produce": 838, "ListOffsets": 0, "Metadata": 1, "FindCoordinator": 0, "SaslHandshake": 0, "ApiVersion": 1, "InitProducerId": 0, "AddPartitionsToTxn": 0, "AddOffsetsToTxn": 0, "EndTxn": 0, "TxnOffsetCommit": 0, "SaslAuthenticate": 0, "OffsetDeleteRequest": 0, "DescribeClientQuotasRequest": 0, "AlterClientQuotasRequest": 0, "DescribeUserScramCredentialsRequest": 0 }, "toppars":{ "benchmark-0": { "topic":"benchmark", "partition":0} } } }, "topics":{ "benchmark": { "topic":"benchmark", "age":26002, "metadata_age":25899, "batchsize": { "min":85524, "max":90970, "avg":88341, "sum":14222968, "stddev": 1222, "p50": 88575, "p75": 89599, "p90": 90111, "p95": 90623, "p99": 91135, "p99_99": 91135, "outofrange": 0, "hdrsize": 14448, "cnt":161 }, "batchcnt": { "min":10000, "max":10000, "avg":10000, "sum":1610000, "stddev": 0, "p50": 10047, "p75": 10047, "p90": 10047, "p95": 10047, "p99": 10047, "p99_99": 10047, "outofrange": 0, "hdrsize": 8304, "cnt":161 }, "partitions":{ "0": { "partition":0, "broker":0, "leader":0, "desired":false, "unknown":false, "msgq_cnt":0, "msgq_bytes":0, "xmit_msgq_cnt":0, "xmit_msgq_bytes":0, "fetchq_cnt":0, "fetchq_size":0, "fetch_state":"none", "query_offset":-1001, "next_offset":0, "app_offset":-1001, "stored_offset":-1001, "commited_offset":-1001, "committed_offset":-1001, "eof_offset":-1001, "lo_offset":-1001, "hi_offset":-1001, "ls_offset":-1001, "consumer_lag":-1, "consumer_lag_stored":-1, "txmsgs":8351666, "txbytes":66813328, "rxmsgs":0, "rxbytes":0, "msgs": 8421666, "rx_ver_drops": 0, "msgs_inflight": 20000, "next_ack_seq": 0, "next_err_seq": 0, "acked_msgid": 0} , "-1": { "partition":-1, "broker":-1, "leader":-1, "desired":false, "unknown":false, "msgq_cnt":0, "msgq_bytes":0, "xmit_msgq_cnt":0, "xmit_msgq_bytes":0, "fetchq_cnt":0, "fetchq_size":0, "fetch_state":"none", "query_offset":-1001, "next_offset":0, "app_offset":-1001, "stored_offset":-1001, "commited_offset":-1001, "committed_offset":-1001, "eof_offset":-1001, "lo_offset":-1001, "hi_offset":-1001, "ls_offset":-1001, "consumer_lag":-1, "consumer_lag_stored":-1, "txmsgs":0, "txbytes":0, "rxmsgs":0, "rxbytes":0, "msgs": 100000, "rx_ver_drops": 0, "msgs_inflight": 0, "next_ack_seq": 0, "next_err_seq": 0, "acked_msgid": 0} } } } , "tx":840, "tx_bytes":73503476, "rx":838, "rx_bytes":51559, "txmsgs":8351666, "txmsg_bytes":66813328, "rxmsgs":0, "rxmsg_bytes":0}
{ "name": "rdkafka#producer-37", "client_id": "rdkafka", "type": "producer", "ts":13406529319, "time":1682592812, "age":28003370, "replyq":0, "msg_cnt":0, "msg_size":0, "msg_max":100000, "msg_size_max":1073741824, "simple_cnt":0, "metadata_cache_cnt":1, "brokers":{ "192.168.0.131:9092/0": { "name":"192.168.0.131:9092/0", "nodeid":0, "nodename":"192.168.0.131:9092", "source":"configured", "state":"UP", "stateage":27900232, "outbuf_cnt":0, "outbuf_msg_cnt":0, "waitresp_cnt":0, "waitresp_msg_cnt":0, "tx":976, "txbytes":85315152, "txerrs":0, "txretries":0, "txidle":526592, "req_timeouts":0, "rx":976, "rxbytes":59977, "rxerrs":0, "rxcorriderrs":0, "rxpartial":0, "rxidle":517540, "zbuf_grow":0, "buf_grow":0, "wakeups":2545, "connects":1, "disconnects":0, "int_latency": { "min":30168, "max":94444, "avg":79522, "sum":106876317283, "stddev": 11111, "p50": 82431, "p75": 88063, "p90": 90623, "p95": 91647, "p99": 93183, "p99_99": 94719, "outofrange": 0, "hdrsize": 12400, "cnt":1343972 }, "outbuf_latency": { "min":17, "max":6050, "avg":2429, "sum":330349, "stddev": 2487, "p50": 691, "p75": 5311, "p90": 5599, "p95": 5855, "p99": 5951, "p99_99": 6079, "outofrange": 0, "hdrsize": 11376, "cnt":136 }, "rtt": { "min":8782, "max":35113, "avg":14671, "sum":2024692, "stddev": 4306, "p50": 14527, "p75": 17663, "p90": 18047, "p95": 20479, "p99": 31871, "p99_99": 35327, "outofrange": 0, "hdrsize": 13424, "cnt":138 }, "throttle": { "min":0, "max":0, "avg":0, "sum":0, "stddev": 0, "p50": 0, "p75": 0, "p90": 0, "p95": 0, "p99": 0, "p99_99": 0, "outofrange": 0, "hdrsize": 17520, "cnt":0 }, "req": { "Produce": 974, "ListOffsets": 0, "Metadata": 1, "FindCoordinator": 0, "SaslHandshake": 0, "ApiVersion": 1, "InitProducerId": 0, "AddPartitionsToTxn": 0, "AddOffsetsToTxn": 0, "EndTxn": 0, "TxnOffsetCommit": 0, "SaslAuthenticate": 0, "OffsetDeleteRequest": 0, "DescribeClientQuotasRequest": 0, "AlterClientQuotasRequest": 0, "DescribeUserScramCredentialsRequest": 0 }, "toppars":{ "benchmark-0": { "topic":"benchmark", "partition":0} } } }, "topics":{ "benchmark": { "topic":"benchmark", "age":28002, "metadata_age":27900, "batchsize": { "min":30975, "max":90808, "avg":86794, "sum":11804060, "stddev": 5267, "p50": 87551, "p75": 89087, "p90": 89599, "p95": 90111, "p99": 90623, "p99_99": 91135, "outofrange": 0, "hdrsize": 14448, "cnt":136 }, "batchcnt": { "min":3972, "max":10000, "avg":9955, "sum":1353972, "stddev": 516, "p50": 10047, "p75": 10047, "p90": 10047, "p95": 10047, "p99": 10047, "p99_99": 10047, "outofrange": 0, "hdrsize": 8304, "cnt":136 }, "partitions":{ "0": { "partition":0, "broker":0, "leader":0, "desired":false, "unknown":false, "msgq_cnt":0, "msgq_bytes":0, "xmit_msgq_cnt":0, "xmit_msgq_bytes":0, "fetchq_cnt":0, "fetchq_size":0, "fetch_state":"none", "query_offset":-1001, "next_offset":0, "app_offset":-1001, "stored_offset":-1001, "commited_offset":-1001, "committed_offset":-1001, "eof_offset":-1001, "lo_offset":-1001, "hi_offset":-1001, "ls_offset":-1001, "consumer_lag":-1, "consumer_lag_stored":-1, "txmsgs":9695638, "txbytes":77565104, "rxmsgs":0, "rxbytes":0, "msgs": 9695638, "rx_ver_drops": 0, "msgs_inflight": 0, "next_ack_seq": 0, "next_err_seq": 0, "acked_msgid": 0} , "-1": { "partition":-1, "broker":-1, "leader":-1, "desired":false, "unknown":false, "msgq_cnt":0, "msgq_bytes":0, "xmit_msgq_cnt":0, "xmit_msgq_bytes":0, "fetchq_cnt":0, "fetchq_size":0, "fetch_state":"none", "query_offset":-1001, "next_offset":0, "app_offset":-1001, "stored_offset":-1001, "commited_offset":-1001, "committed_offset":-1001, "eof_offset":-1001, "lo_offset":-1001, "hi_offset":-1001, "ls_offset":-1001, "consumer_lag":-1, "consumer_lag_stored":-1, "txmsgs":0, "txbytes":0, "rxmsgs":0, "rxbytes":0, "msgs": 100000, "rx_ver_drops": 0, "msgs_inflight": 0, "next_ack_seq": 0, "next_err_seq": 0, "acked_msgid": 0} } } } , "tx":976, "tx_bytes":85315152, "rx":976, "rx_bytes":59977, "txmsgs":9695638, "txmsg_bytes":77565104, "rxmsgs":0, "rxmsg_bytes":0}
{ "name": "rdkafka#producer-37", "client_id": "rdkafka", "type": "producer", "ts":13408529891, "time":1682592814, "age":30003942, "replyq":1, "msg_cnt":0, "msg_size":0, "msg_max":100000, "msg_size_max":1073741824, "simple_cnt":0, "metadata_cache_cnt":1, "brokers":{ "192.168.0.131:9092/0": { "name":"192.168.0.131:9092/0", "nodeid":0, "nodename":"192.168.0.131:9092", "source":"configured", "state":"UP", "stateage":29900804, "outbuf_cnt":0, "outbuf_msg_cnt":0, "waitresp_cnt":0, "waitresp_msg_cnt":0, "tx":976, "txbytes":85315152, "txerrs":0, "txretries":0, "txidle":2527164, "req_timeouts":0, "rx":976, "rxbytes":59977, "rxerrs":0, "rxcorriderrs":0, "rxpartial":0, "rxidle":2518112, "zbuf_grow":0, "buf_grow":0, "wakeups":2545, "connects":1, "disconnects":0, "int_latency": { "min":0, "max":0, "avg":0, "sum":0, "stddev": 0, "p50": 0, "p75": 0, "p90": 0, "p95": 0, "p99": 0, "p99_99": 0, "outofrange": 0, "hdrsize": 12400, "cnt":0 }, "outbuf_latency": { "min":0, "max":0, "avg":0, "sum":0, "stddev": 0, "p50": 0, "p75": 0, "p90": 0, "p95": 0, "p99": 0, "p99_99": 0, "outofrange": 0, "hdrsize": 11376, "cnt":0 }, "rtt": { "min":0, "max":0, "avg":0, "sum":0, "stddev": 0, "p50": 0, "p75": 0, "p90": 0, "p95": 0, "p99": 0, "p99_99": 0, "outofrange": 0, "hdrsize": 13424, "cnt":0 }, "throttle": { "min":0, "max":0, "avg":0, "sum":0, "stddev": 0, "p50": 0, "p75": 0, "p90": 0, "p95": 0, "p99": 0, "p99_99": 0, "outofrange": 0, "hdrsize": 17520, "cnt":0 }, "req": { "Produce": 974, "ListOffsets": 0, "Metadata": 1, "FindCoordinator": 0, "SaslHandshake": 0, "ApiVersion": 1, "InitProducerId": 0, "AddPartitionsToTxn": 0, "AddOffsetsToTxn": 0, "EndTxn": 0, "TxnOffsetCommit": 0, "SaslAuthenticate": 0, "OffsetDeleteRequest": 0, "DescribeClientQuotasRequest": 0, "AlterClientQuotasRequest": 0, "DescribeUserScramCredentialsRequest": 0 }, "toppars":{ "benchmark-0": { "topic":"benchmark", "partition":0} } } }, "topics":{ "benchmark": { "topic":"benchmark", "age":30002, "metadata_age":29900, "batchsize": { "min":0, "max":0, "avg":0, "sum":0, "stddev": 0, "p50": 0, "p75": 0, "p90": 0, "p95": 0, "p99": 0, "p99_99": 0, "outofrange": 0, "hdrsize": 14448, "cnt":0 }, "batchcnt": { "min":0, "max":0, "avg":0, "sum":0, "stddev": 0, "p50": 0, "p75": 0, "p90": 0, "p95": 0, "p99": 0, "p99_99": 0, "outofrange": 0, "hdrsize": 8304, "cnt":0 }, "partitions":{ "0": { "partition":0, "broker":0, "leader":0, "desired":false, "unknown":false, "msgq_cnt":0, "msgq_bytes":0, "xmit_msgq_cnt":0, "xmit_msgq_bytes":0, "fetchq_cnt":0, "fetchq_size":0, "fetch_state":"none", "query_offset":-1001, "next_offset":0, "app_offset":-1001, "stored_offset":-1001, "commited_offset":-1001, "committed_offset":-1001, "eof_offset":-1001, "lo_offset":-1001, "hi_offset":-1001, "ls_offset":-1001, "consumer_lag":-1, "consumer_lag_stored":-1, "txmsgs":9695638, "txbytes":77565104, "rxmsgs":0, "rxbytes":0, "msgs": 9695638, "rx_ver_drops": 0, "msgs_inflight": 0, "next_ack_seq": 0, "next_err_seq": 0, "acked_msgid": 0} , "-1": { "partition":-1, "broker":-1, "leader":-1, "desired":false, "unknown":false, "msgq_cnt":0, "msgq_bytes":0, "xmit_msgq_cnt":0, "xmit_msgq_bytes":0, "fetchq_cnt":0, "fetchq_size":0, "fetch_state":"none", "query_offset":-1001, "next_offset":0, "app_offset":-1001, "stored_offset":-1001, "commited_offset":-1001, "committed_offset":-1001, "eof_offset":-1001, "lo_offset":-1001, "hi_offset":-1001, "ls_offset":-1001, "consumer_lag":-1, "consumer_lag_stored":-1, "txmsgs":0, "txbytes":0, "rxmsgs":0, "rxbytes":0, "msgs": 100000, "rx_ver_drops": 0, "msgs_inflight": 0, "next_ack_seq": 0, "next_err_seq": 0, "acked_msgid": 0} } } } , "tx":976, "tx_bytes":85315152, "rx":976, "rx_bytes":59977, "txmsgs":9695638, "txmsg_bytes":77565104, "rxmsgs":0, "rxmsg_bytes":0}
{ "name": "rdkafka#producer-37", "client_id": "rdkafka", "type": "producer", "ts":13410529926, "time":1682592816, "age":32003977, "replyq":2, "msg_cnt":0, "msg_size":0, "msg_max":100000, "msg_size_max":1073741824, "simple_cnt":0, "metadata_cache_cnt":1, "brokers":{ "192.168.0.131:9092/0": { "name":"192.168.0.131:9092/0", "nodeid":0, "nodename":"192.168.0.131:9092", "source":"configured", "state":"UP", "stateage":31900839, "outbuf_cnt":0, "outbuf_msg_cnt":0, "waitresp_cnt":0, "waitresp_msg_cnt":0, "tx":976, "txbytes":85315152, "txerrs":0, "txretries":0, "txidle":4527199, "req_timeouts":0, "rx":976, "rxbytes":59977, "rxerrs":0, "rxcorriderrs":0, "rxpartial":0, "rxidle":4518147, "zbuf_grow":0, "buf_grow":0, "wakeups":2545, "connects":1, "disconnects":0, "int_latency": { "min":0, "max":0, "avg":0, "sum":0, "stddev": 0, "p50": 0, "p75": 0, "p90": 0, "p95": 0, "p99": 0, "p99_99": 0, "outofrange": 0, "hdrsize": 12400, "cnt":0 }, "outbuf_latency": { "min":0, "max":0, "avg":0, "sum":0, "stddev": 0, "p50": 0, "p75": 0, "p90": 0, "p95": 0, "p99": 0, "p99_99": 0, "outofrange": 0, "hdrsize": 11376, "cnt":0 }, "rtt": { "min":0, "max":0, "avg":0, "sum":0, "stddev": 0, "p50": 0, "p75": 0, "p90": 0, "p95": 0, "p99": 0, "p99_99": 0, "outofrange": 0, "hdrsize": 13424, "cnt":0 }, "throttle": { "min":0, "max":0, "avg":0, "sum":0, "stddev": 0, "p50": 0, "p75": 0, "p90": 0, "p95": 0, "p99": 0, "p99_99": 0, "outofrange": 0, "hdrsize": 17520, "cnt":0 }, "req": { "Produce": 974, "ListOffsets": 0, "Metadata": 1, "FindCoordinator": 0, "SaslHandshake": 0, "ApiVersion": 1, "InitProducerId": 0, "AddPartitionsToTxn": 0, "AddOffsetsToTxn": 0, "EndTxn": 0, "TxnOffsetCommit": 0, "SaslAuthenticate": 0, "OffsetDeleteRequest": 0, "DescribeClientQuotasRequest": 0, "AlterClientQuotasRequest": 0, "DescribeUserScramCredentialsRequest": 0 }, "toppars":{ "benchmark-0": { "topic":"benchmark", "partition":0} } } }, "topics":{ "benchmark": { "topic":"benchmark", "age":32003, "metadata_age":31900, "batchsize": { "min":0, "max":0, "avg":0, "sum":0, "stddev": 0, "p50": 0, "p75": 0, "p90": 0, "p95": 0, "p99": 0, "p99_99": 0, "outofrange": 0, "hdrsize": 14448, "cnt":0 }, "batchcnt": { "min":0, "max":0, "avg":0, "sum":0, "stddev": 0, "p50": 0, "p75": 0, "p90": 0, "p95": 0, "p99": 0, "p99_99": 0, "outofrange": 0, "hdrsize": 8304, "cnt":0 }, "partitions":{ "0": { "partition":0, "broker":0, "leader":0, "desired":false, "unknown":false, "msgq_cnt":0, "msgq_bytes":0, "xmit_msgq_cnt":0, "xmit_msgq_bytes":0, "fetchq_cnt":0, "fetchq_size":0, "fetch_state":"none", "query_offset":-1001, "next_offset":0, "app_offset":-1001, "stored_offset":-1001, "commited_offset":-1001, "committed_offset":-1001, "eof_offset":-1001, "lo_offset":-1001, "hi_offset":-1001, "ls_offset":-1001, "consumer_lag":-1, "consumer_lag_stored":-1, "txmsgs":9695638, "txbytes":77565104, "rxmsgs":0, "rxbytes":0, "msgs": 9695638, "rx_ver_drops": 0, "msgs_inflight": 0, "next_ack_seq": 0, "next_err_seq": 0, "acked_msgid": 0} , "-1": { "partition":-1, "broker":-1, "leader":-1, "desired":false, "unknown":false, "msgq_cnt":0, "msgq_bytes":0, "xmit_msgq_cnt":0, "xmit_msgq_bytes":0, "fetchq_cnt":0, "fetchq_size":0, "fetch_state":"none", "query_offset":-1001, "next_offset":0, "app_offset":-1001, "stored_offset":-1001, "commited_offset":-1001, "committed_offset":-1001, "eof_offset":-1001, "lo_offset":-1001, "hi_offset":-1001, "ls_offset":-1001, "consumer_lag":-1, "consumer_lag_stored":-1, "txmsgs":0, "txbytes":0, "rxmsgs":0, "rxbytes":0, "msgs": 100000, "rx_ver_drops": 0, "msgs_inflight": 0, "next_ack_seq": 0, "next_err_seq": 0, "acked_msgid": 0} } } } , "tx":976, "tx_bytes":85315152, "rx":976, "rx_bytes":59977, "txmsgs":9695638, "txmsg_bytes":77565104, "rxmsgs":0, "rxmsg_bytes":0}
{ "name": "rdkafka#producer-37", "client_id": "rdkafka", "type": "producer", "ts":13412529961, "time":1682592818, "age":34004012, "replyq":3, "msg_cnt":0, "msg_size":0, "msg_max":100000, "msg_size_max":1073741824, "simple_cnt":0, "metadata_cache_cnt":1, "brokers":{ "192.168.0.131:9092/0": { "name":"192.168.0.131:9092/0", "nodeid":0, "nodename":"192.168.0.131:9092", "source":"configured", "state":"UP", "stateage":33900874, "outbuf_cnt":0, "outbuf_msg_cnt":0, "waitresp_cnt":0, "waitresp_msg_cnt":0, "tx":976, "txbytes":85315152, "txerrs":0, "txretries":0, "txidle":6527234, "req_timeouts":0, "rx":976, "rxbytes":59977, "rxerrs":0, "rxcorriderrs":0, "rxpartial":0, "rxidle":6518182, "zbuf_grow":0, "buf_grow":0, "wakeups":2545, "connects":1, "disconnects":0, "int_latency": { "min":0, "max":0, "avg":0, "sum":0, "stddev": 0, "p50": 0, "p75": 0, "p90": 0, "p95": 0, "p99": 0, "p99_99": 0, "outofrange": 0, "hdrsize": 12400, "cnt":0 }, "outbuf_latency": { "min":0, "max":0, "avg":0, "sum":0, "stddev": 0, "p50": 0, "p75": 0, "p90": 0, "p95": 0, "p99": 0, "p99_99": 0, "outofrange": 0, "hdrsize": 11376, "cnt":0 }, "rtt": { "min":0, "max":0, "avg":0, "sum":0, "stddev": 0, "p50": 0, "p75": 0, "p90": 0, "p95": 0, "p99": 0, "p99_99": 0, "outofrange": 0, "hdrsize": 13424, "cnt":0 }, "throttle": { "min":0, "max":0, "avg":0, "sum":0, "stddev": 0, "p50": 0, "p75": 0, "p90": 0, "p95": 0, "p99": 0, "p99_99": 0, "outofrange": 0, "hdrsize": 17520, "cnt":0 }, "req": { "Produce": 974, "ListOffsets": 0, "Metadata": 1, "FindCoordinator": 0, "SaslHandshake": 0, "ApiVersion": 1, "InitProducerId": 0, "AddPartitionsToTxn": 0, "AddOffsetsToTxn": 0, "EndTxn": 0, "TxnOffsetCommit": 0, "SaslAuthenticate": 0, "OffsetDeleteRequest": 0, "DescribeClientQuotasRequest": 0, "AlterClientQuotasRequest": 0, "DescribeUserScramCredentialsRequest": 0 }, "toppars":{ "benchmark-0": { "topic":"benchmark", "partition":0} } } }, "topics":{ "benchmark": { "topic":"benchmark", "age":34003, "metadata_age":33900, "batchsize": { "min":0, "max":0, "avg":0, "sum":0, "stddev": 0, "p50": 0, "p75": 0, "p90": 0, "p95": 0, "p99": 0, "p99_99": 0, "outofrange": 0, "hdrsize": 14448, "cnt":0 }, "batchcnt": { "min":0, "max":0, "avg":0, "sum":0, "stddev": 0, "p50": 0, "p75": 0, "p90": 0, "p95": 0, "p99": 0, "p99_99": 0, "outofrange": 0, "hdrsize": 8304, "cnt":0 }, "partitions":{ "0": { "partition":0, "broker":0, "leader":0, "desired":false, "unknown":false, "msgq_cnt":0, "msgq_bytes":0, "xmit_msgq_cnt":0, "xmit_msgq_bytes":0, "fetchq_cnt":0, "fetchq_size":0, "fetch_state":"none", "query_offset":-1001, "next_offset":0, "app_offset":-1001, "stored_offset":-1001, "commited_offset":-1001, "committed_offset":-1001, "eof_offset":-1001, "lo_offset":-1001, "hi_offset":-1001, "ls_offset":-1001, "consumer_lag":-1, "consumer_lag_stored":-1, "txmsgs":9695638, "txbytes":77565104, "rxmsgs":0, "rxbytes":0, "msgs": 9695638, "rx_ver_drops": 0, "msgs_inflight": 0, "next_ack_seq": 0, "next_err_seq": 0, "acked_msgid": 0} , "-1": { "partition":-1, "broker":-1, "leader":-1, "desired":false, "unknown":false, "msgq_cnt":0, "msgq_bytes":0, "xmit_msgq_cnt":0, "xmit_msgq_bytes":0, "fetchq_cnt":0, "fetchq_size":0, "fetch_state":"none", "query_offset":-1001, "next_offset":0, "app_offset":-1001, "stored_offset":-1001, "commited_offset":-1001, "committed_offset":-1001, "eof_offset":-1001, "lo_offset":-1001, "hi_offset":-1001, "ls_offset":-1001, "consumer_lag":-1, "consumer_lag_stored":-1, "txmsgs":0, "txbytes":0, "rxmsgs":0, "rxbytes":0, "msgs": 100000, "rx_ver_drops": 0, "msgs_inflight": 0, "next_ack_seq": 0, "next_err_seq": 0, "acked_msgid": 0} } } } , "tx":976, "tx_bytes":85315152, "rx":976, "rx_bytes":59977, "txmsgs":9695638, "txmsg_bytes":77565104, "rxmsgs":0, "rxmsg_bytes":0}
{ "name": "rdkafka#producer-37", "client_id": "rdkafka", "type": "producer", "ts":13414529995, "time":1682592820, "age":36004046, "replyq":0, "msg_cnt":100000, "msg_size":800000, "msg_max":100000, "msg_size_max":1073741824, "simple_cnt":0, "metadata_cache_cnt":1, "brokers":{ "192.168.0.131:9092/0": { "name":"192.168.0.131:9092/0", "nodeid":0, "nodename":"192.168.0.131:9092", "source":"configured", "state":"UP", "stateage":35900908, "outbuf_cnt":0, "outbuf_msg_cnt":0, "waitresp_cnt":1, "waitresp_msg_cnt":10000, "tx":1009, "txbytes":88219626, "txerrs":0, "txretries":0, "txidle":6587, "req_timeouts":0, "rx":1008, "rxbytes":61929, "rxerrs":0, "rxcorriderrs":0, "rxpartial":0, "rxidle":9439, "zbuf_grow":0, "buf_grow":0, "wakeups":3436, "connects":1, "disconnects":0, "int_latency": { "min":15, "max":175342, "avg":66445, "sum":22428079864, "stddev": 40615, "p50": 51199, "p75": 93183, "p90": 103423, "p95": 159743, "p99": 167935, "p99_99": 176127, "outofrange": 0, "hdrsize": 12400, "cnt":337540 }, "outbuf_latency": { "min":11, "max":102278, "avg":5748, "sum":189709, "stddev": 17210, "p50": 2655, "p75": 5183, "p90": 5759, "p95": 5791, "p99": 102399, "p99_99": 102399, "outofrange": 0, "hdrsize": 11376, "cnt":33 }, "rtt": { "min":10842, "max":184521, "avg":63516, "sum":2032514, "stddev": 59650, "p50": 30207, "p75": 77823, "p90": 178175, "p95": 178175, "p99": 185343, "p99_99": 185343, "outofrange": 0, "hdrsize": 13424, "cnt":32 }, "throttle": { "min":0, "max":0, "avg":0, "sum":0, "stddev": 0, "p50": 0, "p75": 0, "p90": 0, "p95": 0, "p99": 0, "p99_99": 0, "outofrange": 0, "hdrsize": 17520, "cnt":0 }, "req": { "Produce": 1007, "ListOffsets": 0, "Metadata": 1, "FindCoordinator": 0, "SaslHandshake": 0, "ApiVersion": 1, "InitProducerId": 0, "AddPartitionsToTxn": 0, "AddOffsetsToTxn": 0, "EndTxn": 0, "TxnOffsetCommit": 0, "SaslAuthenticate": 0, "OffsetDeleteRequest": 0, "DescribeClientQuotasRequest": 0, "AlterClientQuotasRequest": 0, "DescribeUserScramCredentialsRequest": 0 }, "toppars":{ "benchmark-0": { "topic":"benchmark", "partition":0} } } }, "topics":{ "benchmark": { "topic":"benchmark", "age":36003, "metadata_age":35900, "batchsize": { "min":67945, "max":90399, "avg":87958, "sum":2902626, "stddev": 3800, "p50": 89087, "p75": 89599, "p90": 90111, "p95": 90623, "p99": 90623, "p99_99": 90623, "outofrange": 0, "hdrsize": 14448, "cnt":33 }, "batchcnt": { "min":7540, "max":10000, "avg":9925, "sum":327540, "stddev": 425, "p50": 10047, "p75": 10047, "p90": 10047, "p95": 10047, "p99": 10047, "p99_99": 10047, "outofrange": 0, "hdrsize": 8304, "cnt":33 }, "partitions":{ "0": { "partition":0, "broker":0, "leader":0, "desired":false, "unknown":false, "msgq_cnt":10500, "msgq_bytes":84000, "xmit_msgq_cnt":0, "xmit_msgq_bytes":0, "fetchq_cnt":0, "fetchq_size":0, "fetch_state":"none", "query_offset":-1001, "next_offset":0, "app_offset":-1001, "stored_offset":-1001, "commited_offset":-1001, "committed_offset":-1001, "eof_offset":-1001, "lo_offset":-1001, "hi_offset":-1001, "ls_offset":-1001, "consumer_lag":-1, "consumer_lag_stored":-1, "txmsgs":10033178, "txbytes":80265424, "rxmsgs":0, "rxbytes":0, "msgs": 10113178, "rx_ver_drops": 0, "msgs_inflight": 10000, "next_ack_seq": 0, "next_err_seq": 0, "acked_msgid": 0} , "-1": { "partition":-1, "broker":-1, "leader":-1, "desired":false, "unknown":false, "msgq_cnt":0, "msgq_bytes":0, "xmit_msgq_cnt":0, "xmit_msgq_bytes":0, "fetchq_cnt":0, "fetchq_size":0, "fetch_state":"none", "query_offset":-1001, "next_offset":0, "app_offset":-1001, "stored_offset":-1001, "commited_offset":-1001, "committed_offset":-1001, "eof_offset":-1001, "lo_offset":-1001, "hi_offset":-1001, "ls_offset":-1001, "consumer_lag":-1, "consumer_lag_stored":-1, "txmsgs":0, "txbytes":0, "rxmsgs":0, "rxbytes":0, "msgs": 100000, "rx_ver_drops": 0, "msgs_inflight": 0, "next_ack_seq": 0, "next_err_seq": 0, "acked_msgid": 0} } } } , "tx":1009, "tx_bytes":88219626, "rx":1008, "rx_bytes":61929, "txmsgs":10033178, "txmsg_bytes":80265424, "rxmsgs":0, "rxmsg_bytes":0}
{ "name": "rdkafka#producer-37", "client_id": "rdkafka", "type": "producer", "ts":13416530374, "time":1682592822, "age":38004425, "replyq":0, "msg_cnt":100000, "msg_size":800000, "msg_max":100000, "msg_size_max":1073741824, "simple_cnt":0, "metadata_cache_cnt":1, "brokers":{ "192.168.0.131:9092/0": { "name":"192.168.0.131:9092/0", "nodeid":0, "nodename":"192.168.0.131:9092", "source":"configured", "state":"UP", "stateage":37901287, "outbuf_cnt":0, "outbuf_msg_cnt":0, "waitresp_cnt":1, "waitresp_msg_cnt":10000, "tx":1157, "txbytes":101253970, "txerrs":0, "txretries":0, "txidle":3581, "req_timeouts":0, "rx":1156, "rxbytes":70957, "rxerrs":0, "rxcorriderrs":0, "rxpartial":0, "rxidle":6378, "zbuf_grow":0, "buf_grow":0, "wakeups":3584, "connects":1, "disconnects":0, "int_latency": { "min":84722, "max":113365, "avg":104796, "sum":155099559641, "stddev": 5600, "p50": 107007, "p75": 109055, "p90": 110591, "p95": 111103, "p99": 112639, "p99_99": 113663, "outofrange": 0, "hdrsize": 12400, "cnt":1480000 }, "outbuf_latency": { "min":24, "max":8817, "avg":2843, "sum":420825, "stddev": 1567, "p50": 2831, "p75": 2991, "p90": 5631, "p95": 5887, "p99": 6335, "p99_99": 8831, "outofrange": 0, "hdrsize": 11376, "cnt":148 }, "rtt": { "min":9976, "max":33519, "avg":13162, "sum":1948010, "stddev": 4556, "p50": 11007, "p75": 13055, "p90": 20991, "p95": 22271, "p99": 31103, "p99_99": 33535, "outofrange": 0, "hdrsize": 13424, "cnt":148 }, "throttle": { "min":0, "max":0, "avg":0, "sum":0, "stddev": 0, "p50": 0, "p75": 0, "p90": 0, "p95": 0, "p99": 0, "p99_99": 0, "outofrange": 0, "hdrsize": 17520, "cnt":0 }, "req": { "Produce": 1155, "ListOffsets": 0, "Metadata": 1, "FindCoordinator": 0, "SaslHandshake": 0, "ApiVersion": 1, "InitProducerId": 0, "AddPartitionsToTxn": 0, "AddOffsetsToTxn": 0, "EndTxn": 0, "TxnOffsetCommit": 0, "SaslAuthenticate": 0, "OffsetDeleteRequest": 0, "DescribeClientQuotasRequest": 0, "AlterClientQuotasRequest": 0, "DescribeUserScramCredentialsRequest": 0 }, "toppars":{ "benchmark-0": { "topic":"benchmark", "partition":0} } } }, "topics":{ "benchmark": { "topic":"benchmark", "age":38003, "metadata_age":37901, "batchsize": { "min":84674, "max":90344, "avg":88013, "sum":13026056, "stddev": 1048, "p50": 88575, "p75": 89087, "p90": 89599, "p95": 89599, "p99": 90111, "p99_99": 90623, "outofrange": 0, "hdrsize": 14448, "cnt":148 }, "batchcnt": { "min":10000, "max":10000, "avg":10000, "sum":1480000, "stddev": 0, "p50": 10047, "p75": 10047, "p90": 10047, "p95": 10047, "p99": 10047, "p99_99": 10047, "outofrange": 0, "hdrsize": 8304, "cnt":148 }, "partitions":{ "0": { "partition":0, "broker":0, "leader":0, "desired":false, "unknown":false, "msgq_cnt":5502, "msgq_bytes":44016, "xmit_msgq_cnt":0, "xmit_msgq_bytes":0, "fetchq_cnt":0, "fetchq_size":0, "fetch_state":"none", "query_offset":-1001, "next_offset":0, "app_offset":-1001, "stored_offset":-1001, "commited_offset":-1001, "committed_offset":-1001, "eof_offset":-1001, "lo_offset":-1001, "hi_offset":-1001, "ls_offset":-1001, "consumer_lag":-1, "consumer_lag_stored":-1, "txmsgs":11513178, "txbytes":92105424, "rxmsgs":0, "rxbytes":0, "msgs": 11593178, "rx_ver_drops": 0, "msgs_inflight": 10000, "next_ack_seq": 0, "next_err_seq": 0, "acked_msgid": 0} , "-1": { "partition":-1, "broker":-1, "leader":-1, "desired":false, "unknown":false, "msgq_cnt":0, "msgq_bytes":0, "xmit_msgq_cnt":0, "xmit_msgq_bytes":0, "fetchq_cnt":0, "fetchq_size":0, "fetch_state":"none", "query_offset":-1001, "next_offset":0, "app_offset":-1001, "stored_offset":-1001, "commited_offset":-1001, "committed_offset":-1001, "eof_offset":-1001, "lo_offset":-1001, "hi_offset":-1001, "ls_offset":-1001, "consumer_lag":-1, "consumer_lag_stored":-1, "txmsgs":0, "txbytes":0, "rxmsgs":0, "rxbytes":0, "msgs": 100000, "rx_ver_drops": 0, "msgs_inflight": 0, "next_ack_seq": 0, "next_err_seq": 0, "acked_msgid": 0} } } } , "tx":1157, "tx_bytes":101253970, "rx":1156, "rx_bytes":70957, "txmsgs":11513178, "txmsg_bytes":92105424, "rxmsgs":0, "rxmsg_bytes":0}
{ "name": "rdkafka#producer-37", "client_id": "rdkafka", "type": "producer", "ts":13418530701, "time":1682592824, "age":40004752, "replyq":0, "msg_cnt":0, "msg_size":0, "msg_max":100000, "msg_size_max":1073741824, "simple_cnt":0, "metadata_cache_cnt":1, "brokers":{ "192.168.0.131:9092/0": { "name":"192.168.0.131:9092/0", "nodeid":0, "nodename":"192.168.0.131:9092", "source":"configured", "state":"UP", "stateage":39901614, "outbuf_cnt":0, "outbuf_msg_cnt":0, "waitresp_cnt":0, "waitresp_msg_cnt":0, "tx":1309, "txbytes":109714546, "txerrs":0, "txretries":0, "txidle":754471, "req_timeouts":0, "rx":1309, "rxbytes":80290, "rxerrs":0, "rxcorriderrs":0, "rxpartial":0, "rxidle":749917, "zbuf_grow":0, "buf_grow":0, "wakeups":40368, "connects":1, "disconnects":0, "int_latency": { "min":1, "max":112532, "avg":65324, "sum":62456269558, "stddev": 47169, "p50": 97791, "p75": 108031, "p90": 110079, "p95": 110591, "p99": 112127, "p99_99": 112639, "outofrange": 0, "hdrsize": 12400, "cnt":956086 }, "outbuf_latency": { "min":11, "max":5550, "avg":1165, "sum":177203, "stddev": 1218, "p50": 509, "p75": 2655, "p90": 2863, "p95": 2895, "p99": 3583, "p99_99": 5567, "outofrange": 0, "hdrsize": 11376, "cnt":152 }, "rtt": { "min":4367, "max":26815, "avg":8862, "sum":1356005, "stddev": 4818, "p50": 6143, "p75": 11007, "p90": 16639, "p95": 17407, "p99": 23935, "p99_99": 26879, "outofrange": 0, "hdrsize": 13424, "cnt":153 }, "throttle": { "min":0, "max":0, "avg":0, "sum":0, "stddev": 0, "p50": 0, "p75": 0, "p90": 0, "p95": 0, "p99": 0, "p99_99": 0, "outofrange": 0, "hdrsize": 17520, "cnt":0 }, "req": { "Produce": 1307, "ListOffsets": 0, "Metadata": 1, "FindCoordinator": 0, "SaslHandshake": 0, "ApiVersion": 1, "InitProducerId": 0, "AddPartitionsToTxn": 0, "AddOffsetsToTxn": 0, "EndTxn": 0, "TxnOffsetCommit": 0, "SaslAuthenticate": 0, "OffsetDeleteRequest": 0, "DescribeClientQuotasRequest": 0, "AlterClientQuotasRequest": 0, "DescribeUserScramCredentialsRequest": 0 }, "toppars":{ "benchmark-0": { "topic":"benchmark", "partition":0} } } }, "topics":{ "benchmark": { "topic":"benchmark", "age":40003, "metadata_age":39901, "batchsize": { "min":20559, "max":92229, "avg":55605, "sum":8452064, "stddev": 29739, "p50": 30335, "p75": 88063, "p90": 89599, "p95": 89599, "p99": 91647, "p99_99": 92671, "outofrange": 0, "hdrsize": 14448, "cnt":152 }, "batchcnt": { "min":2518, "max":10000, "avg":6355, "sum":966086, "stddev": 3359, "p50": 3471, "p75": 10047, "p90": 10047, "p95": 10047, "p99": 10047, "p99_99": 10047, "outofrange": 0, "hdrsize": 8304, "cnt":152 }, "partitions":{ "0": { "partition":0, "broker":0, "leader":0, "desired":false, "unknown":false, "msgq_cnt":0, "msgq_bytes":0, "xmit_msgq_cnt":0, "xmit_msgq_bytes":0, "fetchq_cnt":0, "fetchq_size":0, "fetch_state":"none", "query_offset":-1001, "next_offset":0, "app_offset":-1001, "stored_offset":-1001, "commited_offset":-1001, "committed_offset":-1001, "eof_offset":-1001, "lo_offset":-1001, "hi_offset":-1001, "ls_offset":-1001, "consumer_lag":-1, "consumer_lag_stored":-1, "txmsgs":12469264, "txbytes":99754112, "rxmsgs":0, "rxbytes":0, "msgs": 12469264, "rx_ver_drops": 0, "msgs_inflight": 0, "next_ack_seq": 0, "next_err_seq": 0, "acked_msgid": 0} , "-1": { "partition":-1, "broker":-1, "leader":-1, "desired":false, "unknown":false, "msgq_cnt":0, "msgq_bytes":0, "xmit_msgq_cnt":0, "xmit_msgq_bytes":0, "fetchq_cnt":0, "fetchq_size":0, "fetch_state":"none", "query_offset":-1001, "next_offset":0, "app_offset":-1001, "stored_offset":-1001, "commited_offset":-1001, "committed_offset":-1001, "eof_offset":-1001, "lo_offset":-1001, "hi_offset":-1001, "ls_offset":-1001, "consumer_lag":-1, "consumer_lag_stored":-1, "txmsgs":0, "txbytes":0, "rxmsgs":0, "rxbytes":0, "msgs": 100000, "rx_ver_drops": 0, "msgs_inflight": 0, "next_ack_seq": 0, "next_err_seq": 0, "acked_msgid": 0} } } } , "tx":1309, "tx_bytes":109714546, "rx":1309, "rx_bytes":80290, "txmsgs":12469264, "txmsg_bytes":99754112, "rxmsgs":0, "rxmsg_bytes":0}
{ "name": "rdkafka#producer-37", "client_id": "rdkafka", "type": "producer", "ts":13420531276, "time":1682592826, "age":42005327, "replyq":1, "msg_cnt":0, "msg_size":0, "msg_max":100000, "msg_size_max":1073741824, "simple_cnt":0, "metadata_cache_cnt":1, "brokers":{ "192.168.0.131:9092/0": { "name":"192.168.0.131:9092/0", "nodeid":0, "nodename":"192.168.0.131:9092", "source":"configured", "state":"UP", "stateage":41902189, "outbuf_cnt":0, "outbuf_msg_cnt":0, "waitresp_cnt":0, "waitresp_msg_cnt":0, "tx":1309, "txbytes":109714546, "txerrs":0, "txretries":0, "txidle":2755046, "req_timeouts":0, "rx":1309, "rxbytes":80290, "rxerrs":0, "rxcorriderrs":0, "rxpartial":0, "rxidle":2750492, "zbuf_grow":0, "buf_grow":0, "wakeups":40368, "connects":1, "disconnects":0, "int_latency": { "min":0, "max":0, "avg":0, "sum":0, "stddev": 0, "p50": 0, "p75": 0, "p90": 0, "p95": 0, "p99": 0, "p99_99": 0, "outofrange": 0, "hdrsize": 12400, "cnt":0 }, "outbuf_latency": { "min":0, "max":0, "avg":0, "sum":0, "stddev": 0, "p50": 0, "p75": 0, "p90": 0, "p95": 0, "p99": 0, "p99_99": 0, "outofrange": 0, "hdrsize": 11376, "cnt":0 }, "rtt": { "min":0, "max":0, "avg":0, "sum":0, "stddev": 0, "p50": 0, "p75": 0, "p90": 0, "p95": 0, "p99": 0, "p99_99": 0, "outofrange": 0, "hdrsize": 13424, "cnt":0 }, "throttle": { "min":0, "max":0, "avg":0, "sum":0, "stddev": 0, "p50": 0, "p75": 0, "p90": 0, "p95": 0, "p99": 0, "p99_99": 0, "outofrange": 0, "hdrsize": 17520, "cnt":0 }, "req": { "Produce": 1307, "ListOffsets": 0, "Metadata": 1, "FindCoordinator": 0, "SaslHandshake": 0, "ApiVersion": 1, "InitProducerId": 0, "AddPartitionsToTxn": 0, "AddOffsetsToTxn": 0, "EndTxn": 0, "TxnOffsetCommit": 0, "SaslAuthenticate": 0, "OffsetDeleteRequest": 0, "DescribeClientQuotasRequest": 0, "AlterClientQuotasRequest": 0, "DescribeUserScramCredentialsRequest": 0 }, "toppars":{ "benchmark-0": { "topic":"benchmark", "partition":0} } } }, "topics":{ "benchmark": { "topic":"benchmark", "age":42004, "metadata_age":41902, "batchsize": { "min":0, "max":0, "avg":0, "sum":0, "stddev": 0, "p50": 0, "p75": 0, "p90": 0, "p95": 0, "p99": 0, "p99_99": 0, "outofrange": 0, "hdrsize": 14448, "cnt":0 }, "batchcnt": { "min":0, "max":0, "avg":0, "sum":0, "stddev": 0, "p50": 0, "p75": 0, "p90": 0, "p95": 0, "p99": 0, "p99_99": 0, "outofrange": 0, "hdrsize": 8304, "cnt":0 }, "partitions":{ "0": { "partition":0, "broker":0, "leader":0, "desired":false, "unknown":false, "msgq_cnt":0, "msgq_bytes":0, "xmit_msgq_cnt":0, "xmit_msgq_bytes":0, "fetchq_cnt":0, "fetchq_size":0, "fetch_state":"none", "query_offset":-1001, "next_offset":0, "app_offset":-1001, "stored_offset":-1001, "commited_offset":-1001, "committed_offset":-1001, "eof_offset":-1001, "lo_offset":-1001, "hi_offset":-1001, "ls_offset":-1001, "consumer_lag":-1, "consumer_lag_stored":-1, "txmsgs":12469264, "txbytes":99754112, "rxmsgs":0, "rxbytes":0, "msgs": 12469264, "rx_ver_drops": 0, "msgs_inflight": 0, "next_ack_seq": 0, "next_err_seq": 0, "acked_msgid": 0} , "-1": { "partition":-1, "broker":-1, "leader":-1, "desired":false, "unknown":false, "msgq_cnt":0, "msgq_bytes":0, "xmit_msgq_cnt":0, "xmit_msgq_bytes":0, "fetchq_cnt":0, "fetchq_size":0, "fetch_state":"none", "query_offset":-1001, "next_offset":0, "app_offset":-1001, "stored_offset":-1001, "commited_offset":-1001, "committed_offset":-1001, "eof_offset":-1001, "lo_offset":-1001, "hi_offset":-1001, "ls_offset":-1001, "consumer_lag":-1, "consumer_lag_stored":-1, "txmsgs":0, "txbytes":0, "rxmsgs":0, "rxbytes":0, "msgs": 100000, "rx_ver_drops": 0, "msgs_inflight": 0, "next_ack_seq": 0, "next_err_seq": 0, "acked_msgid": 0} } } } , "tx":1309, "tx_bytes":109714546, "rx":1309, "rx_bytes":80290, "txmsgs":12469264, "txmsg_bytes":99754112, "rxmsgs":0, "rxmsg_bytes":0}
{ "name": "rdkafka#producer-37", "client_id": "rdkafka", "type": "producer", "ts":13422531317, "time":1682592828, "age":44005368, "replyq":2, "msg_cnt":0, "msg_size":0, "msg_max":100000, "msg_size_max":1073741824, "simple_cnt":0, "metadata_cache_cnt":1, "brokers":{ "192.168.0.131:9092/0": { "name":"192.168.0.131:9092/0", "nodeid":0, "nodename":"192.168.0.131:9092", "source":"configured", "state":"UP", "stateage":43902230, "outbuf_cnt":0, "outbuf_msg_cnt":0, "waitresp_cnt":0, "waitresp_msg_cnt":0, "tx":1309, "txbytes":109714546, "txerrs":0, "txretries":0, "txidle":4755087, "req_timeouts":0, "rx":1309, "rxbytes":80290, "rxerrs":0, "rxcorriderrs":0, "rxpartial":0, "rxidle":4750533, "zbuf_grow":0, "buf_grow":0, "wakeups":40368, "connects":1, "disconnects":0, "int_latency": { "min":0, "max":0, "avg":0, "sum":0, "stddev": 0, "p50": 0, "p75": 0, "p90": 0, "p95": 0, "p99": 0, "p99_99": 0, "outofrange": 0, "hdrsize": 12400, "cnt":0 }, "outbuf_latency": { "min":0, "max":0, "avg":0, "sum":0, "stddev": 0, "p50": 0, "p75": 0, "p90": 0, "p95": 0, "p99": 0, "p99_99": 0, "outofrange": 0, "hdrsize": 11376, "cnt":0 }, "rtt": { "min":0, "max":0, "avg":0, "sum":0, "stddev": 0, "p50": 0, "p75": 0, "p90": 0, "p95": 0, "p99": 0, "p99_99": 0, "outofrange": 0, "hdrsize": 13424, "cnt":0 }, "throttle": { "min":0, "max":0, "avg":0, "sum":0, "stddev": 0, "p50": 0, "p75": 0, "p90": 0, "p95": 0, "p99": 0, "p99_99": 0, "outofrange": 0, "hdrsize": 17520, "cnt":0 }, "req": { "Produce": 1307, "ListOffsets": 0, "Metadata": 1, "FindCoordinator": 0, "SaslHandshake": 0, "ApiVersion": 1, "InitProducerId": 0, "AddPartitionsToTxn": 0, "AddOffsetsToTxn": 0, "EndTxn": 0, "TxnOffsetCommit": 0, "SaslAuthenticate": 0, "OffsetDeleteRequest": 0, "DescribeClientQuotasRequest": 0, "AlterClientQuotasRequest": 0, "DescribeUserScramCredentialsRequest": 0 }, "toppars":{ "benchmark-0": { "topic":"benchmark", "partition":0} } } }, "topics":{ "benchmark": { "topic":"benchmark", "age":44004, "metadata_age":43902, "batchsize": { "min":0, "max":0, "avg":0, "sum":0, "stddev": 0, "p50": 0, "p75": 0, "p90": 0, "p95": 0, "p99": 0, "p99_99": 0, "outofrange": 0, "hdrsize": 14448, "cnt":0 }, "batchcnt": { "min":0, "max":0, "avg":0, "sum":0, "stddev": 0, "p50": 0, "p75": 0, "p90": 0, "p95": 0, "p99": 0, "p99_99": 0, "outofrange": 0, "hdrsize": 8304, "cnt":0 }, "partitions":{ "0": { "partition":0, "broker":0, "leader":0, "desired":false, "unknown":false, "msgq_cnt":0, "msgq_bytes":0, "xmit_msgq_cnt":0, "xmit_msgq_bytes":0, "fetchq_cnt":0, "fetchq_size":0, "fetch_state":"none", "query_offset":-1001, "next_offset":0, "app_offset":-1001, "stored_offset":-1001, "commited_offset":-1001, "committed_offset":-1001, "eof_offset":-1001, "lo_offset":-1001, "hi_offset":-1001, "ls_offset":-1001, "consumer_lag":-1, "consumer_lag_stored":-1, "txmsgs":12469264, "txbytes":99754112, "rxmsgs":0, "rxbytes":0, "msgs": 12469264, "rx_ver_drops": 0, "msgs_inflight": 0, "next_ack_seq": 0, "next_err_seq": 0, "acked_msgid": 0} , "-1": { "partition":-1, "broker":-1, "leader":-1, "desired":false, "unknown":false, "msgq_cnt":0, "msgq_bytes":0, "xmit_msgq_cnt":0, "xmit_msgq_bytes":0, "fetchq_cnt":0, "fetchq_size":0, "fetch_state":"none", "query_offset":-1001, "next_offset":0, "app_offset":-1001, "stored_offset":-1001, "commited_offset":-1001, "committed_offset":-1001, "eof_offset":-1001, "lo_offset":-1001, "hi_offset":-1001, "ls_offset":-1001, "consumer_lag":-1, "consumer_lag_stored":-1, "txmsgs":0, "txbytes":0, "rxmsgs":0, "rxbytes":0, "msgs": 100000, "rx_ver_drops": 0, "msgs_inflight": 0, "next_ack_seq": 0, "next_err_seq": 0, "acked_msgid": 0} } } } , "tx":1309, "tx_bytes":109714546, "rx":1309, "rx_bytes":80290, "txmsgs":12469264, "txmsg_bytes":99754112, "rxmsgs":0, "rxmsg_bytes":0}
{ "name": "rdkafka#producer-37", "client_id": "rdkafka", "type": "producer", "ts":13424531352, "time":1682592830, "age":46005403, "replyq":3, "msg_cnt":0, "msg_size":0, "msg_max":100000, "msg_size_max":1073741824, "simple_cnt":0, "metadata_cache_cnt":1, "brokers":{ "192.168.0.131:9092/0": { "name":"192.168.0.131:9092/0", "nodeid":0, "nodename":"192.168.0.131:9092", "source":"configured", "state":"UP", "stateage":45902265, "outbuf_cnt":0, "outbuf_msg_cnt":0, "waitresp_cnt":0, "waitresp_msg_cnt":0, "tx":1309, "txbytes":109714546, "txerrs":0, "txretries":0, "txidle":6755122, "req_timeouts":0, "rx":1309, "rxbytes":80290, "rxerrs":0, "rxcorriderrs":0, "rxpartial":0, "rxidle":6750568, "zbuf_grow":0, "buf_grow":0, "wakeups":40368, "connects":1, "disconnects":0, "int_latency": { "min":0, "max":0, "avg":0, "sum":0, "stddev": 0, "p50": 0, "p75": 0, "p90": 0, "p95": 0, "p99": 0, "p99_99": 0, "outofrange": 0, "hdrsize": 12400, "cnt":0 }, "outbuf_latency": { "min":0, "max":0, "avg":0, "sum":0, "stddev": 0, "p50": 0, "p75": 0, "p90": 0, "p95": 0, "p99": 0, "p99_99": 0, "outofrange": 0, "hdrsize": 11376, "cnt":0 }, "rtt": { "min":0, "max":0, "avg":0, "sum":0, "stddev": 0, "p50": 0, "p75": 0, "p90": 0, "p95": 0, "p99": 0, "p99_99": 0, "outofrange": 0, "hdrsize": 13424, "cnt":0 }, "throttle": { "min":0, "max":0, "avg":0, "sum":0, "stddev": 0, "p50": 0, "p75": 0, "p90": 0, "p95": 0, "p99": 0, "p99_99": 0, "outofrange": 0, "hdrsize": 17520, "cnt":0 }, "req": { "Produce": 1307, "ListOffsets": 0, "Metadata": 1, "FindCoordinator": 0, "SaslHandshake": 0, "ApiVersion": 1, "InitProducerId": 0, "AddPartitionsToTxn": 0, "AddOffsetsToTxn": 0, "EndTxn": 0, "TxnOffsetCommit": 0, "SaslAuthenticate": 0, "OffsetDeleteRequest": 0, "DescribeClientQuotasRequest": 0, "AlterClientQuotasRequest": 0, "DescribeUserScramCredentialsRequest": 0 }, "toppars":{ "benchmark-0": { "topic":"benchmark", "partition":0} } } }, "topics":{ "benchmark": { "topic":"benchmark", "age":46004, "metadata_age":45902, "batchsize": { "min":0, "max":0, "avg":0, "sum":0, "stddev": 0, "p50": 0, "p75": 0, "p90": 0, "p95": 0, "p99": 0, "p99_99": 0, "outofrange": 0, "hdrsize": 14448, "cnt":0 }, "batchcnt": { "min":0, "max":0, "avg":0, "sum":0, "stddev": 0, "p50": 0, "p75": 0, "p90": 0, "p95": 0, "p99": 0, "p99_99": 0, "outofrange": 0, "hdrsize": 8304, "cnt":0 }, "partitions":{ "0": { "partition":0, "broker":0, "leader":0, "desired":false, "unknown":false, "msgq_cnt":0, "msgq_bytes":0, "xmit_msgq_cnt":0, "xmit_msgq_bytes":0, "fetchq_cnt":0, "fetchq_size":0, "fetch_state":"none", "query_offset":-1001, "next_offset":0, "app_offset":-1001, "stored_offset":-1001, "commited_offset":-1001, "committed_offset":-1001, "eof_offset":-1001, "lo_offset":-1001, "hi_offset":-1001, "ls_offset":-1001, "consumer_lag":-1, "consumer_lag_stored":-1, "txmsgs":12469264, "txbytes":99754112, "rxmsgs":0, "rxbytes":0, "msgs": 12469264, "rx_ver_drops": 0, "msgs_inflight": 0, "next_ack_seq": 0, "next_err_seq": 0, "acked_msgid": 0} , "-1": { "partition":-1, "broker":-1, "leader":-1, "desired":false, "unknown":false, "msgq_cnt":0, "msgq_bytes":0, "xmit_msgq_cnt":0, "xmit_msgq_bytes":0, "fetchq_cnt":0, "fetchq_size":0, "fetch_state":"none", "query_offset":-1001, "next_offset":0, "app_offset":-1001, "stored_offset":-1001, "commited_offset":-1001, "committed_offset":-1001, "eof_offset":-1001, "lo_offset":-1001, "hi_offset":-1001, "ls_offset":-1001, "consumer_lag":-1, "consumer_lag_stored":-1, "txmsgs":0, "txbytes":0, "rxmsgs":0, "rxbytes":0, "msgs": 100000, "rx_ver_drops": 0, "msgs_inflight": 0, "next_ack_seq": 0, "next_err_seq": 0, "acked_msgid": 0} } } } , "tx":1309, "tx_bytes":109714546, "rx":1309, "rx_bytes":80290, "txmsgs":12469264, "txmsg_bytes":99754112, "rxmsgs":0, "rxmsg_bytes":0}
{ "name": "rdkafka#producer-37", "client_id": "rdkafka", "type": "producer", "ts":13426531383, "time":1682592832, "age":48005434, "replyq":0, "msg_cnt":100000, "msg_size":800000, "msg_max":100000, "msg_size_max":1073741824, "simple_cnt":0, "metadata_cache_cnt":1, "brokers":{ "192.168.0.131:9092/0": { "name":"192.168.0.131:9092/0", "nodeid":0, "nodename":"192.168.0.131:9092", "source":"configured", "state":"UP", "stateage":47902296, "outbuf_cnt":0, "outbuf_msg_cnt":0, "waitresp_cnt":2, "waitresp_msg_cnt":20000, "tx":1369, "txbytes":115007173, "txerrs":0, "txretries":0, "txidle":4603, "req_timeouts":0, "rx":1367, "rxbytes":83828, "rxerrs":0, "rxcorriderrs":0, "rxpartial":0, "rxidle":7729, "zbuf_grow":0, "buf_grow":0, "wakeups":41203, "connects":1, "disconnects":0, "int_latency": { "min":9, "max":112540, "avg":82982, "sum":50398638543, "stddev": 21393, "p50": 83967, "p75": 96255, "p90": 108031, "p95": 110079, "p99": 112127, "p99_99": 112639, "outofrange": 0, "hdrsize": 12400, "cnt":607337 }, "outbuf_latency": { "min":10, "max":5709, "avg":2570, "sum":154226, "stddev": 1943, "p50": 2831, "p75": 4735, "p90": 5215, "p95": 5343, "p99": 5727, "p99_99": 5727, "outofrange": 0, "hdrsize": 11376, "cnt":60 }, "rtt": { "min":9926, "max":53310, "avg":17344, "sum":1005982, "stddev": 8943, "p50": 13503, "p75": 20095, "p90": 27647, "p95": 34559, "p99": 44031, "p99_99": 53503, "outofrange": 0, "hdrsize": 13424, "cnt":58 }, "throttle": { "min":0, "max":0, "avg":0, "sum":0, "stddev": 0, "p50": 0, "p75": 0, "p90": 0, "p95": 0, "p99": 0, "p99_99": 0, "outofrange": 0, "hdrsize": 17520, "cnt":0 }, "req": { "Produce": 1367, "ListOffsets": 0, "Metadata": 1, "FindCoordinator": 0, "SaslHandshake": 0, "ApiVersion": 1, "InitProducerId": 0, "AddPartitionsToTxn": 0, "AddOffsetsToTxn": 0, "EndTxn": 0, "TxnOffsetCommit": 0, "SaslAuthenticate": 0, "OffsetDeleteRequest": 0, "DescribeClientQuotasRequest": 0, "AlterClientQuotasRequest": 0, "DescribeUserScramCredentialsRequest": 0 }, "toppars":{ "benchmark-0": { "topic":"benchmark", "partition":0} } } }, "topics":{ "benchmark": { "topic":"benchmark", "age":48004, "metadata_age":47902, "batchsize": { "min":66425, "max":90905, "avg":88154, "sum":5289267, "stddev": 3112, "p50": 89087, "p75": 89599, "p90": 90111, "p95": 90623, "p99": 91135, "p99_99": 91135, "outofrange": 0, "hdrsize": 14448, "cnt":60 }, "batchcnt": { "min":7337, "max":10000, "avg":9955, "sum":597337, "stddev": 342, "p50": 10047, "p75": 10047, "p90": 10047, "p95": 10047, "p99": 10047, "p99_99": 10047, "outofrange": 0, "hdrsize": 8304, "cnt":60 }, "partitions":{ "0": { "partition":0, "broker":0, "leader":0, "desired":false, "unknown":false, "msgq_cnt":4955, "msgq_bytes":39640, "xmit_msgq_cnt":0, "xmit_msgq_bytes":0, "fetchq_cnt":0, "fetchq_size":0, "fetch_state":"none", "query_offset":-1001, "next_offset":0, "app_offset":-1001, "stored_offset":-1001, "commited_offset":-1001, "committed_offset":-1001, "eof_offset":-1001, "lo_offset":-1001, "hi_offset":-1001, "ls_offset":-1001, "consumer_lag":-1, "consumer_lag_stored":-1, "txmsgs":13076601, "txbytes":104612808, "rxmsgs":0, "rxbytes":0, "msgs": 13146601, "rx_ver_drops": 0, "msgs_inflight": 20000, "next_ack_seq": 0, "next_err_seq": 0, "acked_msgid": 0} , "-1": { "partition":-1, "broker":-1, "leader":-1, "desired":false, "unknown":false, "msgq_cnt":0, "msgq_bytes":0, "xmit_msgq_cnt":0, "xmit_msgq_bytes":0, "fetchq_cnt":0, "fetchq_size":0, "fetch_state":"none", "query_offset":-1001, "next_offset":0, "app_offset":-1001, "stored_offset":-1001, "commited_offset":-1001, "committed_offset":-1001, "eof_offset":-1001, "lo_offset":-1001, "hi_offset":-1001, "ls_offset":-1001, "consumer_lag":-1, "consumer_lag_stored":-1, "txmsgs":0, "txbytes":0, "rxmsgs":0, "rxbytes":0, "msgs": 100000, "rx_ver_drops": 0, "msgs_inflight": 0, "next_ack_seq": 0, "next_err_seq": 0, "acked_msgid": 0} } } } , "tx":1369, "tx_bytes":115007173, "rx":1367, "rx_bytes":83828, "txmsgs":13076601, "txmsg_bytes":104612808, "rxmsgs":0, "rxmsg_bytes":0}
{ "name": "rdkafka#producer-37", "client_id": "rdkafka", "type": "producer", "ts":13428531740, "time":1682592834, "age":50005791, "replyq":0, "msg_cnt":100000, "msg_size":800000, "msg_max":100000, "msg_size_max":1073741824, "simple_cnt":0, "metadata_cache_cnt":1, "brokers":{ "192.168.0.131:9092/0": { "name":"192.168.0.131:9092/0", "nodeid":0, "nodename":"192.168.0.131:9092", "source":"configured", "state":"UP", "stateage":49902653, "outbuf_cnt":0, "outbuf_msg_cnt":0, "waitresp_cnt":2, "waitresp_msg_cnt":20000, "tx":1540, "txbytes":130070463, "txerrs":0, "txretries":0, "txidle":7712, "req_timeouts":0, "rx":1538, "rxbytes":94259, "rxerrs":0, "rxcorriderrs":0, "rxpartial":0, "rxidle":19637, "zbuf_grow":0, "buf_grow":0, "wakeups":41374, "connects":1, "disconnects":0, "int_latency": { "min":62341, "max":105805, "avg":84922, "sum":145217258499, "stddev": 6257, "p50": 85503, "p75": 89599, "p90": 92159, "p95": 93695, "p99": 99839, "p99_99": 105983, "outofrange": 0, "hdrsize": 12400, "cnt":1710000 }, "outbuf_latency": { "min":11, "max":8028, "avg":2839, "sum":485501, "stddev": 2673, "p50": 2863, "p75": 5599, "p90": 5855, "p95": 5983, "p99": 6335, "p99_99": 8031, "outofrange": 0, "hdrsize": 11376, "cnt":171 }, "rtt": { "min":9178, "max":35781, "avg":15515, "sum":2653232, "stddev": 5147, "p50": 17023, "p75": 17791, "p90": 20863, "p95": 23935, "p99": 34303, "p99_99": 35839, "outofrange": 0, "hdrsize": 13424, "cnt":171 }, "throttle": { "min":0, "max":0, "avg":0, "sum":0, "stddev": 0, "p50": 0, "p75": 0, "p90": 0, "p95": 0, "p99": 0, "p99_99": 0, "outofrange": 0, "hdrsize": 17520, "cnt":0 }, "req": { "Produce": 1538, "ListOffsets": 0, "Metadata": 1, "FindCoordinator": 0, "SaslHandshake": 0, "ApiVersion": 1, "InitProducerId": 0, "AddPartitionsToTxn": 0, "AddOffsetsToTxn": 0, "EndTxn": 0, "TxnOffsetCommit": 0, "SaslAuthenticate": 0, "OffsetDeleteRequest": 0, "DescribeClientQuotasRequest": 0, "AlterClientQuotasRequest": 0, "DescribeUserScramCredentialsRequest": 0 }, "toppars":{ "benchmark-0": { "topic":"benchmark", "partition":0} } } }, "topics":{ "benchmark": { "topic":"benchmark", "age":50004, "metadata_age":49902, "batchsize": { "min":85669, "max":89840, "avg":88033, "sum":15053714, "stddev": 985, "p50": 88575, "p75": 89087, "p90": 89599, "p95": 89599, "p99": 90111, "p99_99": 90111, "outofrange": 0, "hdrsize": 14448, "cnt":171 }, "batchcnt": { "min":10000, "max":10000, "avg":10000, "sum":1710000, "stddev": 0, "p50": 10047, "p75": 10047, "p90": 10047, "p95": 10047, "p99": 10047, "p99_99": 10047, "outofrange": 0, "hdrsize": 8304, "cnt":171 }, "partitions":{ "0": { "partition":0, "broker":0, "leader":0, "desired":false, "unknown":false, "msgq_cnt":0, "msgq_bytes":0, "xmit_msgq_cnt":0, "xmit_msgq_bytes":0, "fetchq_cnt":0, "fetchq_size":0, "fetch_state":"none", "query_offset":-1001, "next_offset":0, "app_offset":-1001, "stored_offset":-1001, "commited_offset":-1001, "committed_offset":-1001, "eof_offset":-1001, "lo_offset":-1001, "hi_offset":-1001, "ls_offset":-1001, "consumer_lag":-1, "consumer_lag_stored":-1, "txmsgs":14786601, "txbytes":118292808, "rxmsgs":0, "rxbytes":0, "msgs": 14856601, "rx_ver_drops": 0, "msgs_inflight": 20000, "next_ack_seq": 0, "next_err_seq": 0, "acked_msgid": 0} , "-1": { "partition":-1, "broker":-1, "leader":-1, "desired":false, "unknown":false, "msgq_cnt":0, "msgq_bytes":0, "xmit_msgq_cnt":0, "xmit_msgq_bytes":0, "fetchq_cnt":0, "fetchq_size":0, "fetch_state":"none", "query_offset":-1001, "next_offset":0, "app_offset":-1001, "stored_offset":-1001, "commited_offset":-1001, "committed_offset":-1001, "eof_offset":-1001, "lo_offset":-1001, "hi_offset":-1001, "ls_offset":-1001, "consumer_lag":-1, "consumer_lag_stored":-1, "txmsgs":0, "txbytes":0, "rxmsgs":0, "rxbytes":0, "msgs": 100000, "rx_ver_drops": 0, "msgs_inflight": 0, "next_ack_seq": 0, "next_err_seq": 0, "acked_msgid": 0} } } } , "tx":1540, "tx_bytes":130070463, "rx":1538, "rx_bytes":94259, "txmsgs":14786601, "txmsg_bytes":118292808, "rxmsgs":0, "rxmsg_bytes":0}
{ "n_cores": 6, "elapsed_time_avg": 3.817776, "bytes_sent": 0 }
